{"name":"AirNeoKG - Explore","id":"7ac94f60-b65a-11ef-b5de-177bf19485d6","categories":[{"id":1,"name":"Client","labels":["Client"],"properties":[{"name":"clientMac","exclude":false,"dataType":"string"},{"name":"clientType","exclude":false,"dataType":"string"},{"name":"clientManufac","exclude":false,"dataType":"string"},{"name":"clientName","exclude":false,"dataType":"number"},{"name":"clientPhy","exclude":false,"dataType":"string"},{"name":"wccFullvalue","exclude":false,"dataType":"bigint"},{"name":"clientCname","exclude":false,"dataType":"string"},{"name":"clientKey","exclude":false,"dataType":"string"}],"createdAt":1733768519512,"lastEditedAt":1733768519512,"color":"#FFE081","size":1,"icon":"D80EB0CA-10FB-45DB-8010-AD6D1B7FE75F","textSize":1,"textAlign":"top","captions":[{"inTooltip":false,"styles":[],"isCaption":false,"key":"Client","type":"label"},{"inTooltip":false,"styles":[],"isCaption":false,"key":"clientCname","type":"property","isGdsData":false},{"inTooltip":false,"styles":[],"isCaption":false,"key":"clientKey","type":"property","isGdsData":false},{"inTooltip":false,"styles":[],"isCaption":false,"key":"clientMac","type":"property","isGdsData":false},{"inTooltip":false,"styles":[],"isCaption":false,"key":"clientManufac","type":"property","isGdsData":false},{"inTooltip":true,"styles":[],"isCaption":true,"key":"clientName","type":"property","isGdsData":false},{"inTooltip":false,"styles":[],"isCaption":false,"key":"clientPhy","type":"property","isGdsData":false},{"inTooltip":false,"styles":[],"isCaption":false,"key":"clientType","type":"property","isGdsData":false},{"inTooltip":false,"styles":[],"isCaption":false,"key":"wccFullvalue","type":"property","isGdsData":false}],"captionKeys":[],"styleRules":[]},{"id":2,"name":"Client Snapshot","labels":["Client Snapshot"],"properties":[{"name":"csnapId","exclude":false,"dataType":"string"},{"name":"csnapFirstseen","exclude":false,"dataType":"bigint"},{"name":"csnapLastseen","exclude":false,"dataType":"bigint"},{"name":"csnapLbssid","exclude":false,"dataType":"string"},{"name":"csnapTimestamp","exclude":false,"dataType":"DateTime"},{"name":"csnapSignalstr","exclude":false,"dataType":"bigint"},{"name":"csnapNcaps","exclude":false,"dataType":"bigint"},{"name":"csnapNprssid","exclude":false,"dataType":"bigint"},{"name":"wccFullvalue","exclude":false,"dataType":"bigint"},{"name":"csnapModtime","exclude":false,"dataType":"bigint"},{"name":"csnapKey","exclude":false,"dataType":"string"}],"createdAt":1733768519512,"lastEditedAt":1733768519512,"color":"#C990C0","size":1,"icon":"5A6FE5FE-050E-4DFA-9021-E5A324C74381","textSize":1,"textAlign":"top","captions":[{"inTooltip":false,"styles":[],"isCaption":false,"key":"Client Snapshot","type":"label"},{"inTooltip":false,"styles":[],"isCaption":false,"key":"csnapFirstseen","type":"property","isGdsData":false},{"inTooltip":true,"styles":[],"isCaption":true,"key":"csnapId","type":"property","isGdsData":false},{"inTooltip":false,"styles":[],"isCaption":false,"key":"csnapKey","type":"property","isGdsData":false},{"inTooltip":false,"styles":[],"isCaption":false,"key":"csnapLastseen","type":"property","isGdsData":false},{"inTooltip":false,"styles":[],"isCaption":false,"key":"csnapLbssid","type":"property","isGdsData":false},{"inTooltip":false,"styles":[],"isCaption":false,"key":"csnapModtime","type":"property","isGdsData":false},{"inTooltip":false,"styles":[],"isCaption":false,"key":"csnapNcaps","type":"property","isGdsData":false},{"inTooltip":false,"styles":[],"isCaption":false,"key":"csnapNprssid","type":"property","isGdsData":false},{"inTooltip":false,"styles":[],"isCaption":false,"key":"csnapSignalstr","type":"property","isGdsData":false},{"inTooltip":false,"styles":[],"isCaption":false,"key":"csnapTimestamp","type":"property","isGdsData":false},{"inTooltip":false,"styles":[],"isCaption":false,"key":"wccFullvalue","type":"property","isGdsData":false}],"captionKeys":[],"styleRules":[]},{"id":3,"name":"Client Signal","labels":["Client Signal"],"properties":[{"name":"wccFullvalue","exclude":false,"dataType":"bigint"},{"name":"csMax","exclude":false,"dataType":"bigint"},{"name":"csFrequency","exclude":false,"dataType":"bigint"},{"name":"csLast","exclude":false,"dataType":"bigint"},{"name":"csMin","exclude":false,"dataType":"bigint"},{"name":"csId","exclude":false,"dataType":"string"},{"name":"csChannel","exclude":false,"dataType":"number"}],"createdAt":1733768519512,"lastEditedAt":1733768519512,"color":"#F79767","size":1,"icon":"DA8D071A-86FF-420F-BFCA-FD652DF80595","textSize":1,"textAlign":"top","captions":[{"inTooltip":false,"styles":[],"isCaption":false,"key":"Client Signal","type":"label"},{"inTooltip":false,"styles":[],"isCaption":false,"key":"csChannel","type":"property","isGdsData":false},{"inTooltip":false,"styles":[],"isCaption":false,"key":"csFrequency","type":"property","isGdsData":false},{"inTooltip":false,"styles":[],"isCaption":false,"key":"csId","type":"property","isGdsData":false},{"inTooltip":false,"styles":[],"isCaption":false,"key":"csLast","type":"property","isGdsData":false},{"inTooltip":false,"styles":[],"isCaption":false,"key":"csMax","type":"property","isGdsData":false},{"inTooltip":false,"styles":[],"isCaption":false,"key":"csMin","type":"property","isGdsData":false},{"inTooltip":true,"styles":[],"isCaption":true,"key":"wccFullvalue","type":"property","isGdsData":false}],"captionKeys":[],"styleRules":[]},{"id":4,"name":"Client Performance","labels":["Client Performance"],"properties":[{"name":"cperfId","exclude":false,"dataType":"string"},{"name":"cperfMaxtxpw","exclude":false,"dataType":"bigint"},{"name":"cperfDatasize","exclude":false,"dataType":"bigint"},{"name":"cperfLinkmeasure","exclude":false,"dataType":"bigint"},{"name":"wccFullvalue","exclude":false,"dataType":"bigint"},{"name":"cperfMintxpw","exclude":false,"dataType":"bigint"},{"name":"cperfDatasizeretry","exclude":false,"dataType":"bigint"}],"createdAt":1733768519512,"lastEditedAt":1733768519512,"color":"#57C7E3","size":1,"icon":"0B36CB73-8B8D-4201-B67E-FAF68F94B2D7","textSize":1,"textAlign":"top","captions":[{"inTooltip":false,"styles":[],"isCaption":false,"key":"Client Performance","type":"label"},{"inTooltip":false,"styles":[],"isCaption":false,"key":"cperfDatasize","type":"property","isGdsData":false},{"inTooltip":false,"styles":[],"isCaption":false,"key":"cperfDatasizeretry","type":"property","isGdsData":false},{"inTooltip":true,"styles":[],"isCaption":true,"key":"cperfId","type":"property","isGdsData":false},{"inTooltip":false,"styles":[],"isCaption":false,"key":"cperfLinkmeasure","type":"property","isGdsData":false},{"inTooltip":false,"styles":[],"isCaption":false,"key":"cperfMaxtxpw","type":"property","isGdsData":false},{"inTooltip":false,"styles":[],"isCaption":false,"key":"cperfMintxpw","type":"property","isGdsData":false},{"inTooltip":false,"styles":[],"isCaption":false,"key":"wccFullvalue","type":"property","isGdsData":false}],"captionKeys":[],"styleRules":[]},{"id":5,"name":"SSID","labels":["SSID"],"properties":[{"name":"ssidLastseen","exclude":false,"dataType":"bigint"},{"name":"ssidProbingdvlen","exclude":false,"dataType":"bigint"},{"name":"ssidEncryptionitem","exclude":false,"dataType":"string"},{"name":"wccFullvalue","exclude":false,"dataType":"bigint"},{"name":"ssideRespdvlen","exclude":false,"dataType":"bigint"},{"name":"ssidAdvdvlen","exclude":false,"dataType":"bigint"},{"name":"ssidFirstseen","exclude":false,"dataType":"bigint"},{"name":"ssidHash","exclude":false,"dataType":"string"},{"name":"ssidEncryption","exclude":false,"dataType":"bigint"},{"name":"ssidName","exclude":false,"dataType":"string"}],"createdAt":1733768519512,"lastEditedAt":1733768519512,"color":"#F16667","size":1,"icon":"BEC8CFFB-AE8C-4FBC-AE83-37A0C94A9C93","textSize":1,"textAlign":"top","captions":[{"inTooltip":false,"styles":[],"isCaption":false,"key":"SSID","type":"label"},{"inTooltip":false,"styles":[],"isCaption":false,"key":"ssidAdvdvlen","type":"property","isGdsData":false},{"inTooltip":false,"styles":[],"isCaption":false,"key":"ssidEncryption","type":"property","isGdsData":false},{"inTooltip":false,"styles":[],"isCaption":false,"key":"ssidEncryptionitem","type":"property","isGdsData":false},{"inTooltip":false,"styles":[],"isCaption":false,"key":"ssideRespdvlen","type":"property","isGdsData":false},{"inTooltip":false,"styles":[],"isCaption":false,"key":"ssidFirstseen","type":"property","isGdsData":false},{"inTooltip":false,"styles":[],"isCaption":false,"key":"ssidHash","type":"property","isGdsData":false},{"inTooltip":false,"styles":[],"isCaption":false,"key":"ssidLastseen","type":"property","isGdsData":false},{"inTooltip":true,"styles":[],"isCaption":true,"key":"ssidName","type":"property","isGdsData":false},{"inTooltip":false,"styles":[],"isCaption":false,"key":"ssidProbingdvlen","type":"property","isGdsData":false},{"inTooltip":false,"styles":[],"isCaption":false,"key":"wccFullvalue","type":"property","isGdsData":false}],"captionKeys":[],"styleRules":[]},{"id":6,"name":"Access Point","labels":["Access Point"],"properties":[{"name":"wccFullvalue","exclude":false,"dataType":"bigint"},{"name":"apCname","exclude":false,"dataType":"string"},{"name":"apKey","exclude":false,"dataType":"string"},{"name":"apType","exclude":false,"dataType":"string"},{"name":"apName","exclude":false,"dataType":"string"},{"name":"apPhy","exclude":false,"dataType":"string"},{"name":"apManufac","exclude":false,"dataType":"string"},{"name":"apMac","exclude":false,"dataType":"string"}],"createdAt":1733768519512,"lastEditedAt":1733768519512,"color":"#D9C8AE","size":1,"icon":"959D2777-ECA0-4C16-93A1-AD1B80C23C85","textSize":1,"textAlign":"top","captions":[{"inTooltip":false,"styles":[],"isCaption":false,"key":"Access Point","type":"label"},{"inTooltip":true,"styles":[],"isCaption":true,"key":"apCname","type":"property","isGdsData":false},{"inTooltip":true,"styles":[],"isCaption":false,"key":"apKey","type":"property","isGdsData":false},{"inTooltip":false,"styles":[],"isCaption":false,"key":"apMac","type":"property","isGdsData":false},{"inTooltip":false,"styles":[],"isCaption":false,"key":"apManufac","type":"property","isGdsData":false},{"inTooltip":false,"styles":[],"isCaption":false,"key":"apName","type":"property","isGdsData":false},{"inTooltip":false,"styles":[],"isCaption":false,"key":"apPhy","type":"property","isGdsData":false},{"inTooltip":false,"styles":[],"isCaption":false,"key":"apType","type":"property","isGdsData":false},{"inTooltip":false,"styles":[],"isCaption":false,"key":"wccFullvalue","type":"property","isGdsData":false}],"captionKeys":[],"styleRules":[]},{"id":7,"name":"Client Device Mobility","labels":["Client Device Mobility"],"properties":[{"name":"wccFullvalue","exclude":false,"dataType":"bigint"},{"name":"cdmobFirstseen","exclude":false,"dataType":"bigint"},{"name":"cdmobSignalchange","exclude":false,"dataType":"bigint"},{"name":"cdmobSeenbycount","exclude":false,"dataType":"bigint"},{"name":"cdmobLastseen","exclude":false,"dataType":"bigint"},{"name":"cdmobKey","exclude":false,"dataType":"string"},{"name":"cdmobLastbssid","exclude":false,"dataType":"string"},{"name":"cdmobId","exclude":false,"dataType":"string"}],"createdAt":1733768519512,"lastEditedAt":1733768519512,"color":"#8DCC93","size":1,"icon":"1854FA5C-8052-47F0-BDCE-33A31BE8C4D8","textSize":1,"textAlign":"top","captions":[{"inTooltip":false,"styles":[],"isCaption":false,"key":"Client Device Mobility","type":"label"},{"inTooltip":false,"styles":[],"isCaption":false,"key":"cdmobFirstseen","type":"property","isGdsData":false},{"inTooltip":false,"styles":[],"isCaption":false,"key":"cdmobId","type":"property","isGdsData":false},{"inTooltip":false,"styles":[],"isCaption":false,"key":"cdmobKey","type":"property","isGdsData":false},{"inTooltip":false,"styles":[],"isCaption":false,"key":"cdmobLastbssid","type":"property","isGdsData":false},{"inTooltip":false,"styles":[],"isCaption":false,"key":"cdmobLastseen","type":"property","isGdsData":false},{"inTooltip":false,"styles":[],"isCaption":false,"key":"cdmobSeenbycount","type":"property","isGdsData":false},{"inTooltip":false,"styles":[],"isCaption":false,"key":"cdmobSignalchange","type":"property","isGdsData":false},{"inTooltip":true,"styles":[],"isCaption":true,"key":"wccFullvalue","type":"property","isGdsData":false}],"captionKeys":[],"styleRules":[]},{"id":8,"name":"Client Security Posture","labels":["Client Security Posture"],"properties":[{"name":"wccFullvalue","exclude":false,"dataType":"bigint"},{"name":"cspProbedSSIDs","exclude":false,"dataType":"string"},{"name":"cspCrypt","exclude":false,"dataType":"number"},{"name":"cspNfrag","exclude":false,"dataType":"bigint"},{"name":"cspLastbssid","exclude":false,"dataType":"string"},{"name":"cspWpslast","exclude":false,"dataType":"bigint"},{"name":"cspNretries","exclude":false,"dataType":"bigint"},{"name":"cspId","exclude":false,"dataType":"string"},{"name":"cspKey","exclude":false,"dataType":"string"},{"name":"cspWpscount","exclude":false,"dataType":"bigint"}],"createdAt":1733768519512,"lastEditedAt":1733768519512,"color":"#ECB5C9","size":1,"icon":"5F002C4A-54ED-4017-B74D-536217435554","textSize":1,"textAlign":"top","captions":[{"inTooltip":false,"styles":[],"isCaption":false,"key":"Client Security Posture","type":"label"},{"inTooltip":false,"styles":[],"isCaption":false,"key":"cspCrypt","type":"property","isGdsData":false},{"inTooltip":false,"styles":[],"isCaption":false,"key":"cspId","type":"property","isGdsData":false},{"inTooltip":false,"styles":[],"isCaption":false,"key":"cspKey","type":"property","isGdsData":false},{"inTooltip":false,"styles":[],"isCaption":false,"key":"cspLastbssid","type":"property","isGdsData":false},{"inTooltip":false,"styles":[],"isCaption":false,"key":"cspNfrag","type":"property","isGdsData":false},{"inTooltip":false,"styles":[],"isCaption":false,"key":"cspNretries","type":"property","isGdsData":false},{"inTooltip":false,"styles":[],"isCaption":false,"key":"cspProbedSSIDs","type":"property","isGdsData":false},{"inTooltip":false,"styles":[],"isCaption":false,"key":"cspWpscount","type":"property","isGdsData":false},{"inTooltip":false,"styles":[],"isCaption":false,"key":"cspWpslast","type":"property","isGdsData":false},{"inTooltip":true,"styles":[],"isCaption":true,"key":"wccFullvalue","type":"property","isGdsData":false}],"captionKeys":[],"styleRules":[]},{"id":9,"name":"WIFI Device","labels":["WIFI Device"],"properties":[{"name":"wccFullvalue","exclude":false,"dataType":"bigint"},{"name":"deviceName","exclude":false,"dataType":"number"},{"name":"deviceKey","exclude":false,"dataType":"string"},{"name":"deviceType","exclude":false,"dataType":"string"},{"name":"devicePhy","exclude":false,"dataType":"string"},{"name":"deviceCname","exclude":false,"dataType":"string"},{"name":"deviceManufac","exclude":false,"dataType":"string"},{"name":"deviceMac","exclude":false,"dataType":"string"}],"createdAt":1733768519512,"lastEditedAt":1733768519512,"color":"#4C8EDA","size":1,"icon":"529856DE-8708-4305-9176-826E85776B56","textSize":1,"textAlign":"top","captions":[{"inTooltip":false,"styles":[],"isCaption":false,"key":"WIFI Device","type":"label"},{"inTooltip":false,"styles":[],"isCaption":false,"key":"deviceCname","type":"property","isGdsData":false},{"inTooltip":false,"styles":[],"isCaption":false,"key":"deviceKey","type":"property","isGdsData":false},{"inTooltip":false,"styles":[],"isCaption":false,"key":"deviceMac","type":"property","isGdsData":false},{"inTooltip":false,"styles":[],"isCaption":false,"key":"deviceManufac","type":"property","isGdsData":false},{"inTooltip":true,"styles":[],"isCaption":true,"key":"deviceName","type":"property","isGdsData":false},{"inTooltip":false,"styles":[],"isCaption":false,"key":"devicePhy","type":"property","isGdsData":false},{"inTooltip":false,"styles":[],"isCaption":false,"key":"deviceType","type":"property","isGdsData":false},{"inTooltip":false,"styles":[],"isCaption":false,"key":"wccFullvalue","type":"property","isGdsData":false}],"captionKeys":[],"styleRules":[]},{"id":10,"name":"WIFI Device Snapshot","labels":["WIFI Device Snapshot"],"properties":[{"name":"wccFullvalue","exclude":false,"dataType":"bigint"},{"name":"devicesnapNcaps","exclude":false,"dataType":"bigint"},{"name":"devicesnapTimestamp","exclude":false,"dataType":"DateTime"},{"name":"devicesnapLastseen","exclude":false,"dataType":"bigint"},{"name":"devicesnapLbssid","exclude":false,"dataType":"string"},{"name":"devicesnapSignalstr","exclude":false,"dataType":"bigint"},{"name":"devicesnapModtime","exclude":false,"dataType":"bigint"},{"name":"devicesnapId","exclude":false,"dataType":"string"},{"name":"devicesnapKey","exclude":false,"dataType":"string"},{"name":"devicesnapFirstseen","exclude":false,"dataType":"bigint"},{"name":"devicesnapNprssid","exclude":false,"dataType":"bigint"}],"createdAt":1733768519512,"lastEditedAt":1733768519512,"color":"#FFC454","size":1,"icon":"C5E61780-4EFE-4435-9E44-9796D7E93E8A","textSize":1,"textAlign":"top","captions":[{"inTooltip":false,"styles":[],"isCaption":false,"key":"WIFI Device Snapshot","type":"label"},{"inTooltip":false,"styles":[],"isCaption":false,"key":"devicesnapFirstseen","type":"property","isGdsData":false},{"inTooltip":false,"styles":[],"isCaption":false,"key":"devicesnapId","type":"property","isGdsData":false},{"inTooltip":false,"styles":[],"isCaption":false,"key":"devicesnapKey","type":"property","isGdsData":false},{"inTooltip":false,"styles":[],"isCaption":false,"key":"devicesnapLastseen","type":"property","isGdsData":false},{"inTooltip":false,"styles":[],"isCaption":false,"key":"devicesnapLbssid","type":"property","isGdsData":false},{"inTooltip":false,"styles":[],"isCaption":false,"key":"devicesnapModtime","type":"property","isGdsData":false},{"inTooltip":false,"styles":[],"isCaption":false,"key":"devicesnapNcaps","type":"property","isGdsData":false},{"inTooltip":false,"styles":[],"isCaption":false,"key":"devicesnapNprssid","type":"property","isGdsData":false},{"inTooltip":false,"styles":[],"isCaption":false,"key":"devicesnapSignalstr","type":"property","isGdsData":false},{"inTooltip":false,"styles":[],"isCaption":false,"key":"devicesnapTimestamp","type":"property","isGdsData":false},{"inTooltip":true,"styles":[],"isCaption":true,"key":"wccFullvalue","type":"property","isGdsData":false}],"captionKeys":[],"styleRules":[]},{"id":11,"name":"WIFI Device Signal","labels":["WIFI Device Signal"],"properties":[{"name":"wccFullvalue","exclude":false,"dataType":"bigint"},{"name":"devicesignalId","exclude":false,"dataType":"string"},{"name":"devicesignalLast","exclude":false,"dataType":"bigint"},{"name":"devicesignalMin","exclude":false,"dataType":"bigint"},{"name":"devicesignalMax","exclude":false,"dataType":"bigint"},{"name":"devicesignalChannel","exclude":false,"dataType":"number"},{"name":"devicesignalFrequency","exclude":false,"dataType":"bigint"}],"createdAt":1733768519512,"lastEditedAt":1733768519512,"color":"#DA7194","size":1,"icon":"43374079-DC16-46D6-A4B2-F4FFDC293018","textSize":1,"textAlign":"top","captions":[{"inTooltip":false,"styles":[],"isCaption":false,"key":"WIFI Device Signal","type":"label"},{"inTooltip":false,"styles":[],"isCaption":false,"key":"devicesignalChannel","type":"property","isGdsData":false},{"inTooltip":false,"styles":[],"isCaption":false,"key":"devicesignalFrequency","type":"property","isGdsData":false},{"inTooltip":false,"styles":[],"isCaption":false,"key":"devicesignalId","type":"property","isGdsData":false},{"inTooltip":false,"styles":[],"isCaption":false,"key":"devicesignalLast","type":"property","isGdsData":false},{"inTooltip":false,"styles":[],"isCaption":false,"key":"devicesignalMax","type":"property","isGdsData":false},{"inTooltip":false,"styles":[],"isCaption":false,"key":"devicesignalMin","type":"property","isGdsData":false},{"inTooltip":true,"styles":[],"isCaption":true,"key":"wccFullvalue","type":"property","isGdsData":false}],"captionKeys":[],"styleRules":[]},{"id":12,"name":"WIFI Device Performance","labels":["WIFI Device Performance"],"properties":[{"name":"wccFullvalue","exclude":false,"dataType":"bigint"},{"name":"deviceperfDatasize","exclude":false,"dataType":"bigint"},{"name":"deviceperfId","exclude":false,"dataType":"string"},{"name":"deviceperfDatasizeretry","exclude":false,"dataType":"bigint"},{"name":"deviceperfLinkmeasure","exclude":false,"dataType":"bigint"},{"name":"deviceperfMintxpw","exclude":false,"dataType":"bigint"},{"name":"deviceperfMaxtxpw","exclude":false,"dataType":"bigint"}],"createdAt":1733768519512,"lastEditedAt":1733768519512,"color":"#569480","size":1,"icon":"E4548064-5766-4BB9-A3E7-8AE7E34B2314","textSize":1,"textAlign":"top","captions":[{"inTooltip":false,"styles":[],"isCaption":false,"key":"WIFI Device Performance","type":"label"},{"inTooltip":false,"styles":[],"isCaption":false,"key":"deviceperfDatasize","type":"property","isGdsData":false},{"inTooltip":false,"styles":[],"isCaption":false,"key":"deviceperfDatasizeretry","type":"property","isGdsData":false},{"inTooltip":false,"styles":[],"isCaption":false,"key":"deviceperfId","type":"property","isGdsData":false},{"inTooltip":false,"styles":[],"isCaption":false,"key":"deviceperfLinkmeasure","type":"property","isGdsData":false},{"inTooltip":false,"styles":[],"isCaption":false,"key":"deviceperfMaxtxpw","type":"property","isGdsData":false},{"inTooltip":false,"styles":[],"isCaption":false,"key":"deviceperfMintxpw","type":"property","isGdsData":false},{"inTooltip":true,"styles":[],"isCaption":true,"key":"wccFullvalue","type":"property","isGdsData":false}],"captionKeys":[],"styleRules":[]},{"id":13,"name":"WIFI Device Mobility","labels":["WIFI Device Mobility"],"properties":[{"name":"devicemobLastbssid","exclude":false,"dataType":"string"},{"name":"devicemobSeenbycount","exclude":false,"dataType":"bigint"},{"name":"wccFullvalue","exclude":false,"dataType":"bigint"},{"name":"devicemobLastseen","exclude":false,"dataType":"bigint"},{"name":"devicemobSignalchange","exclude":false,"dataType":"bigint"},{"name":"devicemobKey","exclude":false,"dataType":"string"},{"name":"devicemobFirstseen","exclude":false,"dataType":"bigint"},{"name":"devicemobId","exclude":false,"dataType":"string"}],"createdAt":1733768519512,"lastEditedAt":1733768519512,"color":"#848484","size":1,"icon":"9746B243-17E0-4840-A1BB-0DF67F1A05E7","textSize":1,"textAlign":"top","captions":[{"inTooltip":false,"styles":[],"isCaption":false,"key":"WIFI Device Mobility","type":"label"},{"inTooltip":false,"styles":[],"isCaption":false,"key":"devicemobFirstseen","type":"property","isGdsData":false},{"inTooltip":false,"styles":[],"isCaption":false,"key":"devicemobId","type":"property","isGdsData":false},{"inTooltip":false,"styles":[],"isCaption":false,"key":"devicemobKey","type":"property","isGdsData":false},{"inTooltip":true,"styles":[],"isCaption":true,"key":"devicemobLastbssid","type":"property","isGdsData":false},{"inTooltip":false,"styles":[],"isCaption":false,"key":"devicemobLastseen","type":"property","isGdsData":false},{"inTooltip":false,"styles":[],"isCaption":false,"key":"devicemobSeenbycount","type":"property","isGdsData":false},{"inTooltip":false,"styles":[],"isCaption":false,"key":"devicemobSignalchange","type":"property","isGdsData":false},{"inTooltip":false,"styles":[],"isCaption":false,"key":"wccFullvalue","type":"property","isGdsData":false}],"captionKeys":[],"styleRules":[]},{"id":14,"name":"WIFI Device Security Posture","labels":["WIFI Device Security Posture"],"properties":[{"name":"devicespLastbssid","exclude":false,"dataType":"string"},{"name":"wccFullvalue","exclude":false,"dataType":"bigint"},{"name":"devicespWpslast","exclude":false,"dataType":"bigint"},{"name":"devicespKey","exclude":false,"dataType":"string"},{"name":"devicespNfrag","exclude":false,"dataType":"bigint"},{"name":"devicespNretries","exclude":false,"dataType":"bigint"},{"name":"devicespProbedSSIDs","exclude":false,"dataType":"number"},{"name":"devicespCrypt","exclude":false,"dataType":"number"},{"name":"devicespWpscount","exclude":false,"dataType":"bigint"},{"name":"devicespId","exclude":false,"dataType":"string"}],"createdAt":1733768519512,"lastEditedAt":1733768519512,"color":"#D9D9D9","size":1,"icon":"EE74976C-3D88-4C75-AAE3-BA272935D480","textSize":1,"textAlign":"top","captions":[{"inTooltip":false,"styles":[],"isCaption":false,"key":"WIFI Device Security Posture","type":"label"},{"inTooltip":false,"styles":[],"isCaption":false,"key":"devicespCrypt","type":"property","isGdsData":false},{"inTooltip":false,"styles":[],"isCaption":false,"key":"devicespId","type":"property","isGdsData":false},{"inTooltip":false,"styles":[],"isCaption":false,"key":"devicespKey","type":"property","isGdsData":false},{"inTooltip":true,"styles":[],"isCaption":true,"key":"devicespLastbssid","type":"property","isGdsData":false},{"inTooltip":false,"styles":[],"isCaption":false,"key":"devicespNfrag","type":"property","isGdsData":false},{"inTooltip":false,"styles":[],"isCaption":false,"key":"devicespNretries","type":"property","isGdsData":false},{"inTooltip":false,"styles":[],"isCaption":false,"key":"devicespProbedSSIDs","type":"property","isGdsData":false},{"inTooltip":false,"styles":[],"isCaption":false,"key":"devicespWpscount","type":"property","isGdsData":false},{"inTooltip":false,"styles":[],"isCaption":false,"key":"devicespWpslast","type":"property","isGdsData":false},{"inTooltip":false,"styles":[],"isCaption":false,"key":"wccFullvalue","type":"property","isGdsData":false}],"captionKeys":[],"styleRules":[]},{"id":15,"name":"WIFI Bridge","labels":["WIFI Bridge"],"properties":[{"name":"wccFullvalue","exclude":false,"dataType":"bigint"},{"name":"brdType","exclude":false,"dataType":"string"},{"name":"brdCname","exclude":false,"dataType":"string"},{"name":"brdName","exclude":false,"dataType":"number"},{"name":"brdManufac","exclude":false,"dataType":"string"},{"name":"brdPhy","exclude":false,"dataType":"string"},{"name":"brdMac","exclude":false,"dataType":"string"},{"name":"brdKey","exclude":false,"dataType":"string"}],"createdAt":1733768519512,"lastEditedAt":1733768519512,"color":"#FFE081","size":1,"icon":"852BB1DD-0514-4FDF-859D-37CA913BB320","textSize":1,"textAlign":"top","captions":[{"inTooltip":false,"styles":[],"isCaption":false,"key":"WIFI Bridge","type":"label"},{"inTooltip":true,"styles":[],"isCaption":true,"key":"brdCname","type":"property","isGdsData":false},{"inTooltip":false,"styles":[],"isCaption":false,"key":"brdKey","type":"property","isGdsData":false},{"inTooltip":false,"styles":[],"isCaption":false,"key":"brdMac","type":"property","isGdsData":false},{"inTooltip":false,"styles":[],"isCaption":false,"key":"brdManufac","type":"property","isGdsData":false},{"inTooltip":false,"styles":[],"isCaption":false,"key":"brdName","type":"property","isGdsData":false},{"inTooltip":false,"styles":[],"isCaption":false,"key":"brdPhy","type":"property","isGdsData":false},{"inTooltip":false,"styles":[],"isCaption":false,"key":"brdType","type":"property","isGdsData":false},{"inTooltip":false,"styles":[],"isCaption":false,"key":"wccFullvalue","type":"property","isGdsData":false}],"captionKeys":[],"styleRules":[]},{"id":16,"name":"WIFI Bridge Snapshot","labels":["WIFI Bridge Snapshot"],"properties":[{"name":"brdsnapNcaps","exclude":false,"dataType":"bigint"},{"name":"brdsnapLastseen","exclude":false,"dataType":"bigint"},{"name":"brdsnapSignalstr","exclude":false,"dataType":"bigint"},{"name":"wccFullvalue","exclude":false,"dataType":"bigint"},{"name":"brdsnapId","exclude":false,"dataType":"string"},{"name":"brdsnapKey","exclude":false,"dataType":"string"},{"name":"brdsnapNprssid","exclude":false,"dataType":"bigint"},{"name":"brdsnapModtime","exclude":false,"dataType":"bigint"},{"name":"brdsnapTimestamp","exclude":false,"dataType":"string"},{"name":"brdsnapLbssid","exclude":false,"dataType":"string"},{"name":"brdsnapFirstseen","exclude":false,"dataType":"bigint"}],"createdAt":1733768519512,"lastEditedAt":1733768519512,"color":"#C990C0","size":1,"icon":"C5E61780-4EFE-4435-9E44-9796D7E93E8A","textSize":1,"textAlign":"top","captions":[{"inTooltip":false,"styles":[],"isCaption":false,"key":"WIFI Bridge Snapshot","type":"label"},{"inTooltip":false,"styles":[],"isCaption":false,"key":"brdsnapFirstseen","type":"property","isGdsData":false},{"inTooltip":false,"styles":[],"isCaption":false,"key":"brdsnapId","type":"property","isGdsData":false},{"inTooltip":false,"styles":[],"isCaption":false,"key":"brdsnapKey","type":"property","isGdsData":false},{"inTooltip":false,"styles":[],"isCaption":false,"key":"brdsnapLastseen","type":"property","isGdsData":false},{"inTooltip":false,"styles":[],"isCaption":false,"key":"brdsnapLbssid","type":"property","isGdsData":false},{"inTooltip":false,"styles":[],"isCaption":false,"key":"brdsnapModtime","type":"property","isGdsData":false},{"inTooltip":true,"styles":[],"isCaption":true,"key":"brdsnapNcaps","type":"property","isGdsData":false},{"inTooltip":false,"styles":[],"isCaption":false,"key":"brdsnapNprssid","type":"property","isGdsData":false},{"inTooltip":false,"styles":[],"isCaption":false,"key":"brdsnapSignalstr","type":"property","isGdsData":false},{"inTooltip":false,"styles":[],"isCaption":false,"key":"brdsnapTimestamp","type":"property","isGdsData":false},{"inTooltip":false,"styles":[],"isCaption":false,"key":"wccFullvalue","type":"property","isGdsData":false}],"captionKeys":[],"styleRules":[]},{"id":17,"name":"WIFI Bridge Signal","labels":["WIFI Bridge Signal"],"properties":[{"name":"brdLast","exclude":false,"dataType":"bigint"},{"name":"wccFullvalue","exclude":false,"dataType":"bigint"},{"name":"brdChannel","exclude":false,"dataType":"bigint"},{"name":"brdFrequency","exclude":false,"dataType":"bigint"},{"name":"brdId","exclude":false,"dataType":"string"},{"name":"brdMax","exclude":false,"dataType":"bigint"},{"name":"brdMin","exclude":false,"dataType":"bigint"}],"createdAt":1733768519512,"lastEditedAt":1733768519512,"color":"#F79767","size":1,"icon":"3246DB01-1F85-41C4-BC3A-4BBFF80BBE89","textSize":1,"textAlign":"top","captions":[{"inTooltip":false,"styles":[],"isCaption":false,"key":"WIFI Bridge Signal","type":"label"},{"inTooltip":false,"styles":[],"isCaption":false,"key":"brdChannel","type":"property","isGdsData":false},{"inTooltip":false,"styles":[],"isCaption":false,"key":"brdFrequency","type":"property","isGdsData":false},{"inTooltip":false,"styles":[],"isCaption":false,"key":"brdId","type":"property","isGdsData":false},{"inTooltip":true,"styles":[],"isCaption":true,"key":"brdLast","type":"property","isGdsData":false},{"inTooltip":false,"styles":[],"isCaption":false,"key":"brdMax","type":"property","isGdsData":false},{"inTooltip":false,"styles":[],"isCaption":false,"key":"brdMin","type":"property","isGdsData":false},{"inTooltip":false,"styles":[],"isCaption":false,"key":"wccFullvalue","type":"property","isGdsData":false}],"captionKeys":[],"styleRules":[]},{"id":18,"name":"WIFI Bridge Performance","labels":["WIFI Bridge Performance"],"properties":[{"name":"wccFullvalue","exclude":false,"dataType":"bigint"},{"name":"brdLinkmeasure","exclude":false,"dataType":"bigint"},{"name":"brdMaxtxpw","exclude":false,"dataType":"bigint"},{"name":"brdId","exclude":false,"dataType":"string"},{"name":"brdDatasize","exclude":false,"dataType":"bigint"},{"name":"brdDatasizeretry","exclude":false,"dataType":"bigint"},{"name":"brdMintxpw","exclude":false,"dataType":"bigint"}],"createdAt":1733768519512,"lastEditedAt":1733768519512,"color":"#57C7E3","size":1,"icon":"4EE2F37B-FBE5-48BE-A97C-498DA1C6A7C4","textSize":1,"textAlign":"top","captions":[{"inTooltip":false,"styles":[],"isCaption":false,"key":"WIFI Bridge Performance","type":"label"},{"inTooltip":false,"styles":[],"isCaption":false,"key":"brdDatasize","type":"property","isGdsData":false},{"inTooltip":false,"styles":[],"isCaption":false,"key":"brdDatasizeretry","type":"property","isGdsData":false},{"inTooltip":false,"styles":[],"isCaption":false,"key":"brdId","type":"property","isGdsData":false},{"inTooltip":false,"styles":[],"isCaption":false,"key":"brdLinkmeasure","type":"property","isGdsData":false},{"inTooltip":false,"styles":[],"isCaption":false,"key":"brdMaxtxpw","type":"property","isGdsData":false},{"inTooltip":false,"styles":[],"isCaption":false,"key":"brdMintxpw","type":"property","isGdsData":false},{"inTooltip":true,"styles":[],"isCaption":true,"key":"wccFullvalue","type":"property","isGdsData":false}],"captionKeys":[],"styleRules":[]},{"id":19,"name":"WIFI Bridge Device Mobility","labels":["WIFI Bridge Device Mobility"],"properties":[{"name":"brdFirstseen","exclude":false,"dataType":"bigint"},{"name":"brdLastseen","exclude":false,"dataType":"bigint"},{"name":"brdSeenbycount","exclude":false,"dataType":"bigint"},{"name":"wccFullvalue","exclude":false,"dataType":"bigint"},{"name":"brdId","exclude":false,"dataType":"string"},{"name":"brdLastbssid","exclude":false,"dataType":"string"},{"name":"brdSignalchange","exclude":false,"dataType":"bigint"},{"name":"brdKey","exclude":false,"dataType":"string"}],"createdAt":1733768519512,"lastEditedAt":1733768519512,"color":"#F16667","size":1,"icon":"3ED9A605-1734-4D72-A516-B6CE413E834F","textSize":1,"textAlign":"top","captions":[{"inTooltip":false,"styles":[],"isCaption":false,"key":"WIFI Bridge Device Mobility","type":"label"},{"inTooltip":true,"styles":[],"isCaption":true,"key":"brdFirstseen","type":"property","isGdsData":false},{"inTooltip":false,"styles":[],"isCaption":false,"key":"brdId","type":"property","isGdsData":false},{"inTooltip":false,"styles":[],"isCaption":false,"key":"brdKey","type":"property","isGdsData":false},{"inTooltip":false,"styles":[],"isCaption":false,"key":"brdLastbssid","type":"property","isGdsData":false},{"inTooltip":false,"styles":[],"isCaption":false,"key":"brdLastseen","type":"property","isGdsData":false},{"inTooltip":false,"styles":[],"isCaption":false,"key":"brdSeenbycount","type":"property","isGdsData":false},{"inTooltip":false,"styles":[],"isCaption":false,"key":"brdSignalchange","type":"property","isGdsData":false},{"inTooltip":false,"styles":[],"isCaption":false,"key":"wccFullvalue","type":"property","isGdsData":false}],"captionKeys":[],"styleRules":[]},{"id":20,"name":"WIFI Bridge Security Posture","labels":["WIFI Bridge Security Posture"],"properties":[{"name":"wccFullvalue","exclude":false,"dataType":"bigint"},{"name":"brdCrypt","exclude":false,"dataType":"number"},{"name":"brdId","exclude":false,"dataType":"string"},{"name":"brdKey","exclude":false,"dataType":"string"},{"name":"brdNretries","exclude":false,"dataType":"bigint"},{"name":"brdProbedSSIDs","exclude":false,"dataType":"number"},{"name":"brdWpscount","exclude":false,"dataType":"bigint"},{"name":"brdLastbssid","exclude":false,"dataType":"string"},{"name":"brdNfrag","exclude":false,"dataType":"bigint"},{"name":"brdWpslast","exclude":false,"dataType":"bigint"}],"createdAt":1733768519512,"lastEditedAt":1733768519512,"color":"#D9C8AE","size":1,"icon":"EE74976C-3D88-4C75-AAE3-BA272935D480","textSize":1,"textAlign":"top","captions":[{"inTooltip":false,"styles":[],"isCaption":false,"key":"WIFI Bridge Security Posture","type":"label"},{"inTooltip":false,"styles":[],"isCaption":false,"key":"brdCrypt","type":"property","isGdsData":false},{"inTooltip":false,"styles":[],"isCaption":false,"key":"brdId","type":"property","isGdsData":false},{"inTooltip":false,"styles":[],"isCaption":false,"key":"brdKey","type":"property","isGdsData":false},{"inTooltip":false,"styles":[],"isCaption":false,"key":"brdLastbssid","type":"property","isGdsData":false},{"inTooltip":false,"styles":[],"isCaption":false,"key":"brdNfrag","type":"property","isGdsData":false},{"inTooltip":false,"styles":[],"isCaption":false,"key":"brdNretries","type":"property","isGdsData":false},{"inTooltip":false,"styles":[],"isCaption":false,"key":"brdProbedSSIDs","type":"property","isGdsData":false},{"inTooltip":false,"styles":[],"isCaption":false,"key":"brdWpscount","type":"property","isGdsData":false},{"inTooltip":false,"styles":[],"isCaption":false,"key":"brdWpslast","type":"property","isGdsData":false},{"inTooltip":true,"styles":[],"isCaption":true,"key":"wccFullvalue","type":"property","isGdsData":false}],"captionKeys":[],"styleRules":[]},{"id":21,"name":"Access Point Snapshot","labels":["Access Point Snapshot"],"properties":[{"name":"wccFullvalue","exclude":false,"dataType":"bigint"},{"name":"apsnapId","exclude":false,"dataType":"string"},{"name":"apsnapKey","exclude":false,"dataType":"string"},{"name":"apsnapLastseen","exclude":false,"dataType":"bigint"},{"name":"apsnapTimestamp","exclude":false,"dataType":"DateTime"},{"name":"apsnapModtime","exclude":false,"dataType":"bigint"},{"name":"apsnapNprssid","exclude":false,"dataType":"bigint"},{"name":"apsnapFirstseen","exclude":false,"dataType":"bigint"},{"name":"apsnapLbssid","exclude":false,"dataType":"string"},{"name":"apsnapNcaps","exclude":false,"dataType":"bigint"},{"name":"apsnapSignalstr","exclude":false,"dataType":"bigint"}],"createdAt":1733768519512,"lastEditedAt":1733768519512,"color":"#8DCC93","size":1,"icon":"852BB1DD-0514-4FDF-859D-37CA913BB320","textSize":1,"textAlign":"top","captions":[{"inTooltip":false,"styles":[],"isCaption":false,"key":"Access Point Snapshot","type":"label"},{"inTooltip":false,"styles":[],"isCaption":false,"key":"apsnapFirstseen","type":"property","isGdsData":false},{"inTooltip":false,"styles":[],"isCaption":false,"key":"apsnapId","type":"property","isGdsData":false},{"inTooltip":false,"styles":[],"isCaption":false,"key":"apsnapKey","type":"property","isGdsData":false},{"inTooltip":false,"styles":[],"isCaption":false,"key":"apsnapLastseen","type":"property","isGdsData":false},{"inTooltip":false,"styles":[],"isCaption":false,"key":"apsnapLbssid","type":"property","isGdsData":false},{"inTooltip":false,"styles":[],"isCaption":false,"key":"apsnapModtime","type":"property","isGdsData":false},{"inTooltip":false,"styles":[],"isCaption":false,"key":"apsnapNcaps","type":"property","isGdsData":false},{"inTooltip":false,"styles":[],"isCaption":false,"key":"apsnapNprssid","type":"property","isGdsData":false},{"inTooltip":false,"styles":[],"isCaption":false,"key":"apsnapSignalstr","type":"property","isGdsData":false},{"inTooltip":false,"styles":[],"isCaption":false,"key":"apsnapTimestamp","type":"property","isGdsData":false},{"inTooltip":true,"styles":[],"isCaption":true,"key":"wccFullvalue","type":"property","isGdsData":false}],"captionKeys":[],"styleRules":[]},{"id":22,"name":"Access Point Signal","labels":["Access Point Signal"],"properties":[{"name":"apId","exclude":false,"dataType":"string"},{"name":"apMin","exclude":false,"dataType":"bigint"},{"name":"apLast","exclude":false,"dataType":"bigint"},{"name":"apFrequency","exclude":false,"dataType":"bigint"},{"name":"wccFullvalue","exclude":false,"dataType":"bigint"},{"name":"apMax","exclude":false,"dataType":"bigint"},{"name":"apChannel","exclude":false,"dataType":"bigint"}],"createdAt":1733768519512,"lastEditedAt":1733768519512,"color":"#ECB5C9","size":1,"icon":"3ED9A605-1734-4D72-A516-B6CE413E834F","textSize":1,"textAlign":"top","captions":[{"inTooltip":false,"styles":[],"isCaption":false,"key":"Access Point Signal","type":"label"},{"inTooltip":false,"styles":[],"isCaption":false,"key":"apChannel","type":"property","isGdsData":false},{"inTooltip":false,"styles":[],"isCaption":false,"key":"apFrequency","type":"property","isGdsData":false},{"inTooltip":true,"styles":[],"isCaption":true,"key":"apId","type":"property","isGdsData":false},{"inTooltip":false,"styles":[],"isCaption":false,"key":"apLast","type":"property","isGdsData":false},{"inTooltip":false,"styles":[],"isCaption":false,"key":"apMax","type":"property","isGdsData":false},{"inTooltip":false,"styles":[],"isCaption":false,"key":"apMin","type":"property","isGdsData":false},{"inTooltip":false,"styles":[],"isCaption":false,"key":"wccFullvalue","type":"property","isGdsData":false}],"captionKeys":[],"styleRules":[]},{"id":23,"name":"Access Point Performance","labels":["Access Point Performance"],"properties":[{"name":"apMintxpw","exclude":false,"dataType":"bigint"},{"name":"apId","exclude":false,"dataType":"string"},{"name":"apMaxtxpw","exclude":false,"dataType":"bigint"},{"name":"wccFullvalue","exclude":false,"dataType":"bigint"},{"name":"apDatasize","exclude":false,"dataType":"bigint"},{"name":"apDatasizeretry","exclude":false,"dataType":"bigint"},{"name":"apLinkmeasure","exclude":false,"dataType":"bigint"}],"createdAt":1733768519512,"lastEditedAt":1733768519512,"color":"#4C8EDA","size":1,"icon":"4EE2F37B-FBE5-48BE-A97C-498DA1C6A7C4","textSize":1,"textAlign":"top","captions":[{"inTooltip":false,"styles":[],"isCaption":false,"key":"Access Point Performance","type":"label"},{"inTooltip":false,"styles":[],"isCaption":false,"key":"apDatasize","type":"property","isGdsData":false},{"inTooltip":false,"styles":[],"isCaption":false,"key":"apDatasizeretry","type":"property","isGdsData":false},{"inTooltip":false,"styles":[],"isCaption":false,"key":"apId","type":"property","isGdsData":false},{"inTooltip":false,"styles":[],"isCaption":false,"key":"apLinkmeasure","type":"property","isGdsData":false},{"inTooltip":false,"styles":[],"isCaption":false,"key":"apMaxtxpw","type":"property","isGdsData":false},{"inTooltip":true,"styles":[],"isCaption":true,"key":"apMintxpw","type":"property","isGdsData":false},{"inTooltip":false,"styles":[],"isCaption":false,"key":"wccFullvalue","type":"property","isGdsData":false}],"captionKeys":[],"styleRules":[]},{"id":24,"name":"Access Point Device Mobility","labels":["Access Point Device Mobility"],"properties":[{"name":"apLastbssid","exclude":false,"dataType":"string"},{"name":"apId","exclude":false,"dataType":"string"},{"name":"apSeenbycount","exclude":false,"dataType":"bigint"},{"name":"apFirstseen","exclude":false,"dataType":"bigint"},{"name":"wccFullvalue","exclude":false,"dataType":"bigint"},{"name":"apKey","exclude":false,"dataType":"string"},{"name":"apSignalchange","exclude":false,"dataType":"bigint"},{"name":"apLastseen","exclude":false,"dataType":"bigint"}],"createdAt":1733768519512,"lastEditedAt":1733768519512,"color":"#FFC454","size":1,"icon":"1CA7DA46-C910-4486-B227-906F4CEDD9D4","textSize":1,"textAlign":"top","captions":[{"inTooltip":false,"styles":[],"isCaption":false,"key":"Access Point Device Mobility","type":"label"},{"inTooltip":false,"styles":[],"isCaption":false,"key":"apFirstseen","type":"property","isGdsData":false},{"inTooltip":false,"styles":[],"isCaption":false,"key":"apId","type":"property","isGdsData":false},{"inTooltip":false,"styles":[],"isCaption":false,"key":"apKey","type":"property","isGdsData":false},{"inTooltip":true,"styles":[],"isCaption":true,"key":"apLastbssid","type":"property","isGdsData":false},{"inTooltip":false,"styles":[],"isCaption":false,"key":"apLastseen","type":"property","isGdsData":false},{"inTooltip":false,"styles":[],"isCaption":false,"key":"apSeenbycount","type":"property","isGdsData":false},{"inTooltip":false,"styles":[],"isCaption":false,"key":"apSignalchange","type":"property","isGdsData":false},{"inTooltip":false,"styles":[],"isCaption":false,"key":"wccFullvalue","type":"property","isGdsData":false}],"captionKeys":[],"styleRules":[]},{"id":25,"name":"Access Point Security Posture","labels":["Access Point Security Posture"],"properties":[{"name":"apNretries","exclude":false,"dataType":"bigint"},{"name":"wccFullvalue","exclude":false,"dataType":"bigint"},{"name":"apLastbssid","exclude":false,"dataType":"string"},{"name":"apId","exclude":false,"dataType":"string"},{"name":"apCrypt","exclude":false,"dataType":"string"},{"name":"apWpslast","exclude":false,"dataType":"bigint"},{"name":"apNfrag","exclude":false,"dataType":"bigint"},{"name":"apWpscount","exclude":false,"dataType":"bigint"},{"name":"apKey","exclude":false,"dataType":"string"},{"name":"apProbedSSIDs","exclude":false,"dataType":"string"}],"createdAt":1733768519512,"lastEditedAt":1733768519512,"color":"#DA7194","size":1,"icon":"EE74976C-3D88-4C75-AAE3-BA272935D480","textSize":1,"textAlign":"top","captions":[{"inTooltip":false,"styles":[],"isCaption":false,"key":"Access Point Security Posture","type":"label"},{"inTooltip":false,"styles":[],"isCaption":false,"key":"apCrypt","type":"property","isGdsData":false},{"inTooltip":false,"styles":[],"isCaption":false,"key":"apId","type":"property","isGdsData":false},{"inTooltip":false,"styles":[],"isCaption":false,"key":"apKey","type":"property","isGdsData":false},{"inTooltip":false,"styles":[],"isCaption":false,"key":"apLastbssid","type":"property","isGdsData":false},{"inTooltip":false,"styles":[],"isCaption":false,"key":"apNfrag","type":"property","isGdsData":false},{"inTooltip":true,"styles":[],"isCaption":true,"key":"apNretries","type":"property","isGdsData":false},{"inTooltip":false,"styles":[],"isCaption":false,"key":"apProbedSSIDs","type":"property","isGdsData":false},{"inTooltip":false,"styles":[],"isCaption":false,"key":"apWpscount","type":"property","isGdsData":false},{"inTooltip":false,"styles":[],"isCaption":false,"key":"apWpslast","type":"property","isGdsData":false},{"inTooltip":false,"styles":[],"isCaption":false,"key":"wccFullvalue","type":"property","isGdsData":false}],"captionKeys":[],"styleRules":[]},{"id":26,"name":"SSID Snapshot","labels":["SSID Snapshot"],"properties":[{"name":"ssidsnapTimestamp","exclude":false,"dataType":"DateTime"},{"name":"wccFullvalue","exclude":false,"dataType":"bigint"},{"name":"ssidsnapProbingDevices","exclude":false,"dataType":"string"},{"name":"ssidsnapAdvertisingdevices","exclude":false,"dataType":"string"},{"name":"ssidsnapRespondingdevices","exclude":false,"dataType":"string"},{"name":"ssidsnapId","exclude":false,"dataType":"string"},{"name":"ssidsnapName","exclude":false,"dataType":"string"},{"name":"ssidsnapHash","exclude":false,"dataType":"bigint"}],"createdAt":1733768519512,"lastEditedAt":1733768519512,"color":"#569480","size":1,"icon":"C5E61780-4EFE-4435-9E44-9796D7E93E8A","textSize":1,"textAlign":"top","captions":[{"inTooltip":false,"styles":[],"isCaption":false,"key":"SSID Snapshot","type":"label"},{"inTooltip":false,"styles":[],"isCaption":false,"key":"ssidsnapAdvertisingdevices","type":"property","isGdsData":false},{"inTooltip":false,"styles":[],"isCaption":false,"key":"ssidsnapHash","type":"property","isGdsData":false},{"inTooltip":false,"styles":[],"isCaption":false,"key":"ssidsnapId","type":"property","isGdsData":false},{"inTooltip":true,"styles":[],"isCaption":true,"key":"ssidsnapName","type":"property","isGdsData":false},{"inTooltip":false,"styles":[],"isCaption":false,"key":"ssidsnapProbingDevices","type":"property","isGdsData":false},{"inTooltip":false,"styles":[],"isCaption":false,"key":"ssidsnapRespondingdevices","type":"property","isGdsData":false},{"inTooltip":false,"styles":[],"isCaption":false,"key":"ssidsnapTimestamp","type":"property","isGdsData":false},{"inTooltip":false,"styles":[],"isCaption":false,"key":"wccFullvalue","type":"property","isGdsData":false}],"captionKeys":[],"styleRules":[]}],"labels":{"Client":[{"propertyKey":"clientMac","type":"Client","dataType":"string"},{"propertyKey":"clientType","type":"Client","dataType":"string"},{"propertyKey":"clientManufac","type":"Client","dataType":"string"},{"propertyKey":"clientName","type":"Client","dataType":"number"},{"propertyKey":"clientPhy","type":"Client","dataType":"string"},{"propertyKey":"clientKey","type":"Client","dataType":"string"},{"propertyKey":"clientCname","type":"Client","dataType":"string"},{"propertyKey":"wccFullvalue","type":"Client","dataType":"bigint"}],"Client Snapshot":[{"propertyKey":"csnapId","type":"Client Snapshot","dataType":"string"},{"propertyKey":"csnapFirstseen","type":"Client Snapshot","dataType":"bigint"},{"propertyKey":"csnapLastseen","type":"Client Snapshot","dataType":"bigint"},{"propertyKey":"csnapLbssid","type":"Client Snapshot","dataType":"string"},{"propertyKey":"csnapTimestamp","type":"Client Snapshot","dataType":"DateTime"},{"propertyKey":"csnapSignalstr","type":"Client Snapshot","dataType":"bigint"},{"propertyKey":"csnapNcaps","type":"Client Snapshot","dataType":"bigint"},{"propertyKey":"csnapNprssid","type":"Client Snapshot","dataType":"bigint"},{"propertyKey":"csnapModtime","type":"Client Snapshot","dataType":"bigint"},{"propertyKey":"csnapKey","type":"Client Snapshot","dataType":"string"},{"propertyKey":"wccFullvalue","type":"Client Snapshot","dataType":"bigint"}],"Client Signal":[{"propertyKey":"csId","type":"Client Signal","dataType":"string"},{"propertyKey":"csChannel","type":"Client Signal","dataType":"number"},{"propertyKey":"csFrequency","type":"Client Signal","dataType":"bigint"},{"propertyKey":"csMin","type":"Client Signal","dataType":"number"},{"propertyKey":"csMax","type":"Client Signal","dataType":"number"},{"propertyKey":"csLast","type":"Client Signal","dataType":"number"},{"propertyKey":"wccFullvalue","type":"Client Signal","dataType":"bigint"}],"Client Performance":[{"propertyKey":"cperfId","type":"Client Performance","dataType":"string"},{"propertyKey":"cperfMaxtxpw","type":"Client Performance","dataType":"bigint"},{"propertyKey":"cperfDatasize","type":"Client Performance","dataType":"bigint"},{"propertyKey":"cperfLinkmeasure","type":"Client Performance","dataType":"bigint"},{"propertyKey":"cperfMintxpw","type":"Client Performance","dataType":"bigint"},{"propertyKey":"cperfDatasizeretry","type":"Client Performance","dataType":"bigint"},{"propertyKey":"wccFullvalue","type":"Client Performance","dataType":"bigint"}],"SSID":[{"propertyKey":"ssidName","type":"SSID","dataType":"number"},{"propertyKey":"ssidLastseen","type":"SSID","dataType":"bigint"},{"propertyKey":"ssidFirstseen","type":"SSID","dataType":"bigint"},{"propertyKey":"ssidEncryption","type":"SSID","dataType":"bigint"},{"propertyKey":"ssidHash","type":"SSID","dataType":"string"},{"propertyKey":"ssideRespdvlen","type":"SSID","dataType":"bigint"},{"propertyKey":"ssidProbingdvlen","type":"SSID","dataType":"bigint"},{"propertyKey":"ssidEncryptionitem","type":"SSID","dataType":"string"},{"propertyKey":"ssidAdvdvlen","type":"SSID","dataType":"bigint"},{"propertyKey":"wccFullvalue","type":"SSID","dataType":"bigint"}],"Access Point":[{"propertyKey":"apMac","type":"Access Point","dataType":"string"},{"propertyKey":"apType","type":"Access Point","dataType":"string"},{"propertyKey":"apManufac","type":"Access Point","dataType":"string"},{"propertyKey":"apPhy","type":"Access Point","dataType":"string"},{"propertyKey":"apName","type":"Access Point","dataType":"string"},{"propertyKey":"apKey","type":"Access Point","dataType":"string"},{"propertyKey":"apCname","type":"Access Point","dataType":"string"},{"propertyKey":"wccFullvalue","type":"Access Point","dataType":"bigint"}],"Client Device Mobility":[{"propertyKey":"cdmobId","type":"Client Device Mobility","dataType":"string"},{"propertyKey":"cdmobLastbssid","type":"Client Device Mobility","dataType":"string"},{"propertyKey":"cdmobLastseen","type":"Client Device Mobility","dataType":"bigint"},{"propertyKey":"cdmobFirstseen","type":"Client Device Mobility","dataType":"bigint"},{"propertyKey":"cdmobSignalchange","type":"Client Device Mobility","dataType":"bigint"},{"propertyKey":"cdmobSeenbycount","type":"Client Device Mobility","dataType":"bigint"},{"propertyKey":"cdmobKey","type":"Client Device Mobility","dataType":"string"},{"propertyKey":"wccFullvalue","type":"Client Device Mobility","dataType":"bigint"}],"Client Security Posture":[{"propertyKey":"cspId","type":"Client Security Posture","dataType":"string"},{"propertyKey":"cspWpscount","type":"Client Security Posture","dataType":"bigint"},{"propertyKey":"cspProbedSSIDs","type":"Client Security Posture","dataType":"number"},{"propertyKey":"cspKey","type":"Client Security Posture","dataType":"string"},{"propertyKey":"cspLastbssid","type":"Client Security Posture","dataType":"string"},{"propertyKey":"cspNfrag","type":"Client Security Posture","dataType":"bigint"},{"propertyKey":"cspCrypt","type":"Client Security Posture","dataType":"number"},{"propertyKey":"cspNretries","type":"Client Security Posture","dataType":"bigint"},{"propertyKey":"cspWpslast","type":"Client Security Posture","dataType":"bigint"},{"propertyKey":"wccFullvalue","type":"Client Security Posture","dataType":"bigint"}],"WIFI Device":[{"propertyKey":"deviceKey","type":"WIFI Device","dataType":"string"},{"propertyKey":"deviceType","type":"WIFI Device","dataType":"string"},{"propertyKey":"deviceManufac","type":"WIFI Device","dataType":"string"},{"propertyKey":"deviceCname","type":"WIFI Device","dataType":"string"},{"propertyKey":"deviceMac","type":"WIFI Device","dataType":"string"},{"propertyKey":"devicePhy","type":"WIFI Device","dataType":"string"},{"propertyKey":"deviceName","type":"WIFI Device","dataType":"number"},{"propertyKey":"wccFullvalue","type":"WIFI Device","dataType":"bigint"}],"WIFI Device Snapshot":[{"propertyKey":"devicesnapId","type":"WIFI Device Snapshot","dataType":"string"},{"propertyKey":"devicesnapFirstseen","type":"WIFI Device Snapshot","dataType":"bigint"},{"propertyKey":"devicesnapSignalstr","type":"WIFI Device Snapshot","dataType":"bigint"},{"propertyKey":"devicesnapLastseen","type":"WIFI Device Snapshot","dataType":"bigint"},{"propertyKey":"devicesnapKey","type":"WIFI Device Snapshot","dataType":"string"},{"propertyKey":"devicesnapNcaps","type":"WIFI Device Snapshot","dataType":"bigint"},{"propertyKey":"devicesnapNprssid","type":"WIFI Device Snapshot","dataType":"bigint"},{"propertyKey":"devicesnapTimestamp","type":"WIFI Device Snapshot","dataType":"DateTime"},{"propertyKey":"devicesnapModtime","type":"WIFI Device Snapshot","dataType":"bigint"},{"propertyKey":"devicesnapLbssid","type":"WIFI Device Snapshot","dataType":"string"},{"propertyKey":"wccFullvalue","type":"WIFI Device Snapshot","dataType":"bigint"}],"WIFI Device Signal":[{"propertyKey":"devicesignalId","type":"WIFI Device Signal","dataType":"string"},{"propertyKey":"devicesignalChannel","type":"WIFI Device Signal","dataType":"number"},{"propertyKey":"devicesignalLast","type":"WIFI Device Signal","dataType":"bigint"},{"propertyKey":"devicesignalMin","type":"WIFI Device Signal","dataType":"bigint"},{"propertyKey":"devicesignalMax","type":"WIFI Device Signal","dataType":"bigint"},{"propertyKey":"devicesignalFrequency","type":"WIFI Device Signal","dataType":"bigint"},{"propertyKey":"wccFullvalue","type":"WIFI Device Signal","dataType":"bigint"}],"WIFI Device Performance":[{"propertyKey":"deviceperfId","type":"WIFI Device Performance","dataType":"string"},{"propertyKey":"deviceperfMintxpw","type":"WIFI Device Performance","dataType":"bigint"},{"propertyKey":"deviceperfDatasize","type":"WIFI Device Performance","dataType":"bigint"},{"propertyKey":"deviceperfMaxtxpw","type":"WIFI Device Performance","dataType":"bigint"},{"propertyKey":"deviceperfDatasizeretry","type":"WIFI Device Performance","dataType":"bigint"},{"propertyKey":"deviceperfLinkmeasure","type":"WIFI Device Performance","dataType":"bigint"},{"propertyKey":"wccFullvalue","type":"WIFI Device Performance","dataType":"bigint"}],"WIFI Device Mobility":[{"propertyKey":"devicemobId","type":"WIFI Device Mobility","dataType":"string"},{"propertyKey":"devicemobLastseen","type":"WIFI Device Mobility","dataType":"bigint"},{"propertyKey":"devicemobLastbssid","type":"WIFI Device Mobility","dataType":"string"},{"propertyKey":"devicemobSeenbycount","type":"WIFI Device Mobility","dataType":"bigint"},{"propertyKey":"devicemobFirstseen","type":"WIFI Device Mobility","dataType":"bigint"},{"propertyKey":"devicemobSignalchange","type":"WIFI Device Mobility","dataType":"bigint"},{"propertyKey":"devicemobKey","type":"WIFI Device Mobility","dataType":"string"},{"propertyKey":"wccFullvalue","type":"WIFI Device Mobility","dataType":"bigint"}],"WIFI Device Security Posture":[{"propertyKey":"devicespId","type":"WIFI Device Security Posture","dataType":"string"},{"propertyKey":"devicespWpslast","type":"WIFI Device Security Posture","dataType":"bigint"},{"propertyKey":"devicespCrypt","type":"WIFI Device Security Posture","dataType":"number"},{"propertyKey":"devicespProbedSSIDs","type":"WIFI Device Security Posture","dataType":"number"},{"propertyKey":"devicespNretries","type":"WIFI Device Security Posture","dataType":"bigint"},{"propertyKey":"devicespLastbssid","type":"WIFI Device Security Posture","dataType":"string"},{"propertyKey":"devicespWpscount","type":"WIFI Device Security Posture","dataType":"bigint"},{"propertyKey":"devicespKey","type":"WIFI Device Security Posture","dataType":"string"},{"propertyKey":"devicespNfrag","type":"WIFI Device Security Posture","dataType":"bigint"},{"propertyKey":"wccFullvalue","type":"WIFI Device Security Posture","dataType":"bigint"}],"WIFI Bridge":[{"propertyKey":"brdKey","type":"WIFI Bridge","dataType":"string"},{"propertyKey":"brdType","type":"WIFI Bridge","dataType":"string"},{"propertyKey":"brdMac","type":"WIFI Bridge","dataType":"string"},{"propertyKey":"brdCname","type":"WIFI Bridge","dataType":"string"},{"propertyKey":"brdPhy","type":"WIFI Bridge","dataType":"string"},{"propertyKey":"brdName","type":"WIFI Bridge","dataType":"number"},{"propertyKey":"brdManufac","type":"WIFI Bridge","dataType":"string"},{"propertyKey":"wccFullvalue","type":"WIFI Bridge","dataType":"bigint"}],"WIFI Bridge Snapshot":[{"propertyKey":"brdsnapId","type":"WIFI Bridge Snapshot","dataType":"string"},{"propertyKey":"brdsnapModtime","type":"WIFI Bridge Snapshot","dataType":"bigint"},{"propertyKey":"brdsnapLbssid","type":"WIFI Bridge Snapshot","dataType":"string"},{"propertyKey":"brdsnapKey","type":"WIFI Bridge Snapshot","dataType":"string"},{"propertyKey":"brdsnapFirstseen","type":"WIFI Bridge Snapshot","dataType":"bigint"},{"propertyKey":"brdsnapLastseen","type":"WIFI Bridge Snapshot","dataType":"bigint"},{"propertyKey":"brdsnapNcaps","type":"WIFI Bridge Snapshot","dataType":"bigint"},{"propertyKey":"brdsnapTimestamp","type":"WIFI Bridge Snapshot","dataType":"string"},{"propertyKey":"brdsnapSignalstr","type":"WIFI Bridge Snapshot","dataType":"bigint"},{"propertyKey":"brdsnapNprssid","type":"WIFI Bridge Snapshot","dataType":"bigint"},{"propertyKey":"wccFullvalue","type":"WIFI Bridge Snapshot","dataType":"bigint"}],"WIFI Bridge Signal":[{"propertyKey":"brdId","type":"WIFI Bridge Signal","dataType":"string"},{"propertyKey":"brdMax","type":"WIFI Bridge Signal","dataType":"bigint"},{"propertyKey":"brdFrequency","type":"WIFI Bridge Signal","dataType":"bigint"},{"propertyKey":"brdLast","type":"WIFI Bridge Signal","dataType":"bigint"},{"propertyKey":"brdMin","type":"WIFI Bridge Signal","dataType":"bigint"},{"propertyKey":"brdChannel","type":"WIFI Bridge Signal","dataType":"bigint"},{"propertyKey":"wccFullvalue","type":"WIFI Bridge Signal","dataType":"bigint"}],"WIFI Bridge Performance":[{"propertyKey":"brdId","type":"WIFI Bridge Performance","dataType":"string"},{"propertyKey":"brdMintxpw","type":"WIFI Bridge Performance","dataType":"bigint"},{"propertyKey":"brdMaxtxpw","type":"WIFI Bridge Performance","dataType":"bigint"},{"propertyKey":"brdDatasize","type":"WIFI Bridge Performance","dataType":"bigint"},{"propertyKey":"brdDatasizeretry","type":"WIFI Bridge Performance","dataType":"bigint"},{"propertyKey":"brdLinkmeasure","type":"WIFI Bridge Performance","dataType":"bigint"},{"propertyKey":"wccFullvalue","type":"WIFI Bridge Performance","dataType":"bigint"}],"WIFI Bridge Device Mobility":[{"propertyKey":"brdKey","type":"WIFI Bridge Device Mobility","dataType":"string"},{"propertyKey":"brdId","type":"WIFI Bridge Device Mobility","dataType":"string"},{"propertyKey":"brdSeenbycount","type":"WIFI Bridge Device Mobility","dataType":"bigint"},{"propertyKey":"brdFirstseen","type":"WIFI Bridge Device Mobility","dataType":"bigint"},{"propertyKey":"brdLastseen","type":"WIFI Bridge Device Mobility","dataType":"bigint"},{"propertyKey":"brdLastbssid","type":"WIFI Bridge Device Mobility","dataType":"string"},{"propertyKey":"brdSignalchange","type":"WIFI Bridge Device Mobility","dataType":"bigint"},{"propertyKey":"wccFullvalue","type":"WIFI Bridge Device Mobility","dataType":"bigint"}],"WIFI Bridge Security Posture":[{"propertyKey":"brdKey","type":"WIFI Bridge Security Posture","dataType":"string"},{"propertyKey":"brdId","type":"WIFI Bridge Security Posture","dataType":"string"},{"propertyKey":"brdLastbssid","type":"WIFI Bridge Security Posture","dataType":"string"},{"propertyKey":"brdProbedSSIDs","type":"WIFI Bridge Security Posture","dataType":"number"},{"propertyKey":"brdNretries","type":"WIFI Bridge Security Posture","dataType":"bigint"},{"propertyKey":"brdNfrag","type":"WIFI Bridge Security Posture","dataType":"bigint"},{"propertyKey":"brdCrypt","type":"WIFI Bridge Security Posture","dataType":"number"},{"propertyKey":"brdWpscount","type":"WIFI Bridge Security Posture","dataType":"bigint"},{"propertyKey":"brdWpslast","type":"WIFI Bridge Security Posture","dataType":"bigint"},{"propertyKey":"wccFullvalue","type":"WIFI Bridge Security Posture","dataType":"bigint"}],"Access Point Snapshot":[{"propertyKey":"apsnapId","type":"Access Point Snapshot","dataType":"string"},{"propertyKey":"apsnapLbssid","type":"Access Point Snapshot","dataType":"string"},{"propertyKey":"apsnapFirstseen","type":"Access Point Snapshot","dataType":"bigint"},{"propertyKey":"apsnapSignalstr","type":"Access Point Snapshot","dataType":"bigint"},{"propertyKey":"apsnapLastseen","type":"Access Point Snapshot","dataType":"bigint"},{"propertyKey":"apsnapKey","type":"Access Point Snapshot","dataType":"string"},{"propertyKey":"apsnapNprssid","type":"Access Point Snapshot","dataType":"bigint"},{"propertyKey":"apsnapNcaps","type":"Access Point Snapshot","dataType":"bigint"},{"propertyKey":"apsnapTimestamp","type":"Access Point Snapshot","dataType":"DateTime"},{"propertyKey":"apsnapModtime","type":"Access Point Snapshot","dataType":"bigint"},{"propertyKey":"wccFullvalue","type":"Access Point Snapshot","dataType":"bigint"}],"Access Point Signal":[{"propertyKey":"apId","type":"Access Point Signal","dataType":"string"},{"propertyKey":"apLast","type":"Access Point Signal","dataType":"number"},{"propertyKey":"apChannel","type":"Access Point Signal","dataType":"bigint"},{"propertyKey":"apFrequency","type":"Access Point Signal","dataType":"bigint"},{"propertyKey":"apMin","type":"Access Point Signal","dataType":"number"},{"propertyKey":"apMax","type":"Access Point Signal","dataType":"number"},{"propertyKey":"wccFullvalue","type":"Access Point Signal","dataType":"bigint"}],"Access Point Performance":[{"propertyKey":"apId","type":"Access Point Performance","dataType":"string"},{"propertyKey":"apDatasizeretry","type":"Access Point Performance","dataType":"bigint"},{"propertyKey":"apLinkmeasure","type":"Access Point Performance","dataType":"bigint"},{"propertyKey":"apDatasize","type":"Access Point Performance","dataType":"bigint"},{"propertyKey":"apMaxtxpw","type":"Access Point Performance","dataType":"bigint"},{"propertyKey":"apMintxpw","type":"Access Point Performance","dataType":"bigint"},{"propertyKey":"wccFullvalue","type":"Access Point Performance","dataType":"bigint"}],"Access Point Device Mobility":[{"propertyKey":"apKey","type":"Access Point Device Mobility","dataType":"string"},{"propertyKey":"apId","type":"Access Point Device Mobility","dataType":"string"},{"propertyKey":"apSignalchange","type":"Access Point Device Mobility","dataType":"bigint"},{"propertyKey":"apFirstseen","type":"Access Point Device Mobility","dataType":"bigint"},{"propertyKey":"apSeenbycount","type":"Access Point Device Mobility","dataType":"bigint"},{"propertyKey":"apLastbssid","type":"Access Point Device Mobility","dataType":"string"},{"propertyKey":"apLastseen","type":"Access Point Device Mobility","dataType":"bigint"},{"propertyKey":"wccFullvalue","type":"Access Point Device Mobility","dataType":"bigint"}],"Access Point Security Posture":[{"propertyKey":"apKey","type":"Access Point Security Posture","dataType":"string"},{"propertyKey":"apId","type":"Access Point Security Posture","dataType":"string"},{"propertyKey":"apLastbssid","type":"Access Point Security Posture","dataType":"string"},{"propertyKey":"apWpslast","type":"Access Point Security Posture","dataType":"bigint"},{"propertyKey":"apNfrag","type":"Access Point Security Posture","dataType":"bigint"},{"propertyKey":"apWpscount","type":"Access Point Security Posture","dataType":"bigint"},{"propertyKey":"apCrypt","type":"Access Point Security Posture","dataType":"string"},{"propertyKey":"apProbedSSIDs","type":"Access Point Security Posture","dataType":"number"},{"propertyKey":"apNretries","type":"Access Point Security Posture","dataType":"bigint"},{"propertyKey":"wccFullvalue","type":"Access Point Security Posture","dataType":"bigint"}],"SSID Snapshot":[{"propertyKey":"ssidsnapRespondingdevices","type":"SSID Snapshot","dataType":"string"},{"propertyKey":"ssidsnapHash","type":"SSID Snapshot","dataType":"bigint"},{"propertyKey":"ssidsnapAdvertisingdevices","type":"SSID Snapshot","dataType":"string"},{"propertyKey":"ssidsnapProbingDevices","type":"SSID Snapshot","dataType":"number"},{"propertyKey":"ssidsnapTimestamp","type":"SSID Snapshot","dataType":"DateTime"},{"propertyKey":"ssidsnapId","type":"SSID Snapshot","dataType":"string"},{"propertyKey":"ssidsnapName","type":"SSID Snapshot","dataType":"string"},{"propertyKey":"wccFullvalue","type":"SSID Snapshot","dataType":"bigint"}],"_Neodash_Dashboard":[{"propertyKey":"uuid","type":"_Neodash_Dashboard","dataType":"string"},{"propertyKey":"title","type":"_Neodash_Dashboard","dataType":"string"},{"propertyKey":"version","type":"_Neodash_Dashboard","dataType":"string"},{"propertyKey":"user","type":"_Neodash_Dashboard","dataType":"string"},{"propertyKey":"content","type":"_Neodash_Dashboard","dataType":"string"},{"propertyKey":"date","type":"_Neodash_Dashboard","dataType":"DateTime"}]},"relationshipTypes":[{"id":"ASSOCIATED_TO_CLIENT_SNAPSHOT_FIRST","name":"ASSOCIATED_TO_CLIENT_SNAPSHOT_FIRST","properties":[],"color":"#848484","size":1,"textSize":1,"textAlign":"top","captions":[{"inTooltip":true,"isCaption":true,"styles":[],"key":"ASSOCIATED_TO_CLIENT_SNAPSHOT_FIRST","type":"relationship"}],"captionKeys":[],"styleRules":[]},{"id":"ASSOCIATED_TO_CLIENT_SNAPSHOT_LAST","name":"ASSOCIATED_TO_CLIENT_SNAPSHOT_LAST","properties":[],"color":"#848484","size":1,"textSize":1,"textAlign":"top","captions":[{"inTooltip":true,"isCaption":true,"styles":[],"key":"ASSOCIATED_TO_CLIENT_SNAPSHOT_LAST","type":"relationship"}],"captionKeys":[],"styleRules":[]},{"id":"NEXT_CLIENT_SNAPSHOT","name":"NEXT_CLIENT_SNAPSHOT","properties":[],"color":"#848484","size":1,"textSize":1,"textAlign":"top","captions":[{"inTooltip":true,"isCaption":true,"styles":[],"key":"NEXT_CLIENT_SNAPSHOT","type":"relationship"}],"captionKeys":[],"styleRules":[]},{"id":"ASSOCIATED_TO_CLIENT_SIGNAL","name":"ASSOCIATED_TO_CLIENT_SIGNAL","properties":[],"color":"#848484","size":1,"textSize":1,"textAlign":"top","captions":[{"inTooltip":true,"isCaption":true,"styles":[],"key":"ASSOCIATED_TO_CLIENT_SIGNAL","type":"relationship"}],"captionKeys":[],"styleRules":[]},{"id":"ASSOCIATED_TO_CLIENT_PERFORMANCE","name":"ASSOCIATED_TO_CLIENT_PERFORMANCE","properties":[],"color":"#848484","size":1,"textSize":1,"textAlign":"top","captions":[{"inTooltip":true,"isCaption":true,"styles":[],"key":"ASSOCIATED_TO_CLIENT_PERFORMANCE","type":"relationship"}],"captionKeys":[],"styleRules":[]},{"id":"ASSOCIATED_TO_CLIENT_DEVICE_MOBILITY","name":"ASSOCIATED_TO_CLIENT_DEVICE_MOBILITY","properties":[],"color":"#848484","size":1,"textSize":1,"textAlign":"top","captions":[{"inTooltip":true,"isCaption":true,"styles":[],"key":"ASSOCIATED_TO_CLIENT_DEVICE_MOBILITY","type":"relationship"}],"captionKeys":[],"styleRules":[]},{"id":"ASSOCIATED_TO_CLIENT_SECURITY_POSTURE","name":"ASSOCIATED_TO_CLIENT_SECURITY_POSTURE","properties":[],"color":"#848484","size":1,"textSize":1,"textAlign":"top","captions":[{"inTooltip":true,"isCaption":true,"styles":[],"key":"ASSOCIATED_TO_CLIENT_SECURITY_POSTURE","type":"relationship"}],"captionKeys":[],"styleRules":[]},{"id":"ASSOCIATED_TO_WIFI_DEVICE_SIGNAL","name":"ASSOCIATED_TO_WIFI_DEVICE_SIGNAL","properties":[],"color":"#848484","size":1,"textSize":1,"textAlign":"top","captions":[{"inTooltip":true,"isCaption":true,"styles":[],"key":"ASSOCIATED_TO_WIFI_DEVICE_SIGNAL","type":"relationship"}],"captionKeys":[],"styleRules":[]},{"id":"ASSOCIATED_TO_WIFI_DEVICE_SNAPSHOT_FIRST","name":"ASSOCIATED_TO_WIFI_DEVICE_SNAPSHOT_FIRST","properties":[],"color":"#848484","size":1,"textSize":1,"textAlign":"top","captions":[{"inTooltip":true,"isCaption":true,"styles":[],"key":"ASSOCIATED_TO_WIFI_DEVICE_SNAPSHOT_FIRST","type":"relationship"}],"captionKeys":[],"styleRules":[]},{"id":"ASSOCIATED_TO_WIFI_DEVICE_SNAPSHOT_LAST","name":"ASSOCIATED_TO_WIFI_DEVICE_SNAPSHOT_LAST","properties":[],"color":"#848484","size":1,"textSize":1,"textAlign":"top","captions":[{"inTooltip":true,"isCaption":true,"styles":[],"key":"ASSOCIATED_TO_WIFI_DEVICE_SNAPSHOT_LAST","type":"relationship"}],"captionKeys":[],"styleRules":[]},{"id":"ASSOCIATED_TO_WIFI_DEVICE_PERFORMANCE","name":"ASSOCIATED_TO_WIFI_DEVICE_PERFORMANCE","properties":[],"color":"#848484","size":1,"textSize":1,"textAlign":"top","captions":[{"inTooltip":true,"isCaption":true,"styles":[],"key":"ASSOCIATED_TO_WIFI_DEVICE_PERFORMANCE","type":"relationship"}],"captionKeys":[],"styleRules":[]},{"id":"ASSOCIATED_TO_WIFI_DEVICE_MOBILITY","name":"ASSOCIATED_TO_WIFI_DEVICE_MOBILITY","properties":[],"color":"#848484","size":1,"textSize":1,"textAlign":"top","captions":[{"inTooltip":true,"isCaption":true,"styles":[],"key":"ASSOCIATED_TO_WIFI_DEVICE_MOBILITY","type":"relationship"}],"captionKeys":[],"styleRules":[]},{"id":"ASSOCIATED_TO_WIFI_DEVICE_SECURITY_POSTURE","name":"ASSOCIATED_TO_WIFI_DEVICE_SECURITY_POSTURE","properties":[],"color":"#848484","size":1,"textSize":1,"textAlign":"top","captions":[{"inTooltip":true,"isCaption":true,"styles":[],"key":"ASSOCIATED_TO_WIFI_DEVICE_SECURITY_POSTURE","type":"relationship"}],"captionKeys":[],"styleRules":[]},{"id":"ASSOCIATED_TO_WIFI_BRIDGE_SNAPSHOT_FIRST","name":"ASSOCIATED_TO_WIFI_BRIDGE_SNAPSHOT_FIRST","properties":[],"color":"#848484","size":1,"textSize":1,"textAlign":"top","captions":[{"inTooltip":true,"isCaption":true,"styles":[],"key":"ASSOCIATED_TO_WIFI_BRIDGE_SNAPSHOT_FIRST","type":"relationship"}],"captionKeys":[],"styleRules":[]},{"id":"ASSOCIATED_TO_WIFI_BRIDGE_SNAPSHOT_LAST","name":"ASSOCIATED_TO_WIFI_BRIDGE_SNAPSHOT_LAST","properties":[],"color":"#848484","size":1,"textSize":1,"textAlign":"top","captions":[{"inTooltip":true,"isCaption":true,"styles":[],"key":"ASSOCIATED_TO_WIFI_BRIDGE_SNAPSHOT_LAST","type":"relationship"}],"captionKeys":[],"styleRules":[]},{"id":"ASSOCIATED_TO_WIFI_BRIDGE_SIGNAL","name":"ASSOCIATED_TO_WIFI_BRIDGE_SIGNAL","properties":[],"color":"#848484","size":1,"textSize":1,"textAlign":"top","captions":[{"inTooltip":true,"isCaption":true,"styles":[],"key":"ASSOCIATED_TO_WIFI_BRIDGE_SIGNAL","type":"relationship"}],"captionKeys":[],"styleRules":[]},{"id":"ASSOCIATED_TO_WIFI_BRIDGE_PERFORMANCE","name":"ASSOCIATED_TO_WIFI_BRIDGE_PERFORMANCE","properties":[],"color":"#848484","size":1,"textSize":1,"textAlign":"top","captions":[{"inTooltip":true,"isCaption":true,"styles":[],"key":"ASSOCIATED_TO_WIFI_BRIDGE_PERFORMANCE","type":"relationship"}],"captionKeys":[],"styleRules":[]},{"id":"ASSOCIATED_TO_WIFI_BRIDGE_DEVICE_MOBILITY","name":"ASSOCIATED_TO_WIFI_BRIDGE_DEVICE_MOBILITY","properties":[],"color":"#848484","size":1,"textSize":1,"textAlign":"top","captions":[{"inTooltip":true,"isCaption":true,"styles":[],"key":"ASSOCIATED_TO_WIFI_BRIDGE_DEVICE_MOBILITY","type":"relationship"}],"captionKeys":[],"styleRules":[]},{"id":"ASSOCIATED_TO_WIFI_BRIDGE_SECURITY_POSTURE","name":"ASSOCIATED_TO_WIFI_BRIDGE_SECURITY_POSTURE","properties":[],"color":"#848484","size":1,"textSize":1,"textAlign":"top","captions":[{"inTooltip":true,"isCaption":true,"styles":[],"key":"ASSOCIATED_TO_WIFI_BRIDGE_SECURITY_POSTURE","type":"relationship"}],"captionKeys":[],"styleRules":[]},{"id":"ASSOCIATED_TO_ACCESS_POINT_SNAPSHOT_FIRST","name":"ASSOCIATED_TO_ACCESS_POINT_SNAPSHOT_FIRST","properties":[],"color":"#848484","size":1,"textSize":1,"textAlign":"top","captions":[{"inTooltip":true,"isCaption":true,"styles":[],"key":"ASSOCIATED_TO_ACCESS_POINT_SNAPSHOT_FIRST","type":"relationship"}],"captionKeys":[],"styleRules":[]},{"id":"ASSOCIATED_TO_ACCESS_POINT_SNAPSHOT_LAST","name":"ASSOCIATED_TO_ACCESS_POINT_SNAPSHOT_LAST","properties":[],"color":"#848484","size":1,"textSize":1,"textAlign":"top","captions":[{"inTooltip":true,"isCaption":true,"styles":[],"key":"ASSOCIATED_TO_ACCESS_POINT_SNAPSHOT_LAST","type":"relationship"}],"captionKeys":[],"styleRules":[]},{"id":"ASSOCIATED_TO_ACCESS_POINT_SIGNAL","name":"ASSOCIATED_TO_ACCESS_POINT_SIGNAL","properties":[],"color":"#848484","size":1,"textSize":1,"textAlign":"top","captions":[{"inTooltip":true,"isCaption":true,"styles":[],"key":"ASSOCIATED_TO_ACCESS_POINT_SIGNAL","type":"relationship"}],"captionKeys":[],"styleRules":[]},{"id":"ASSOCIATED_TO_ACCESS_POINT_PERFORMANCE","name":"ASSOCIATED_TO_ACCESS_POINT_PERFORMANCE","properties":[],"color":"#848484","size":1,"textSize":1,"textAlign":"top","captions":[{"inTooltip":true,"isCaption":true,"styles":[],"key":"ASSOCIATED_TO_ACCESS_POINT_PERFORMANCE","type":"relationship"}],"captionKeys":[],"styleRules":[]},{"id":"ASSOCIATED_TO_ACCESS_POINT_DEVICE_MOBILITY","name":"ASSOCIATED_TO_ACCESS_POINT_DEVICE_MOBILITY","properties":[],"color":"#848484","size":1,"textSize":1,"textAlign":"top","captions":[{"inTooltip":true,"isCaption":true,"styles":[],"key":"ASSOCIATED_TO_ACCESS_POINT_DEVICE_MOBILITY","type":"relationship"}],"captionKeys":[],"styleRules":[]},{"id":"ASSOCIATED_TO_ACCESS_POINT_SECURITY_POSTURE","name":"ASSOCIATED_TO_ACCESS_POINT_SECURITY_POSTURE","properties":[],"color":"#848484","size":1,"textSize":1,"textAlign":"top","captions":[{"inTooltip":true,"isCaption":true,"styles":[],"key":"ASSOCIATED_TO_ACCESS_POINT_SECURITY_POSTURE","type":"relationship"}],"captionKeys":[],"styleRules":[]},{"id":"ASSOCIATED_TO_SSID_SNAPSHOT_FIRST","name":"ASSOCIATED_TO_SSID_SNAPSHOT_FIRST","properties":[],"color":"#848484","size":1,"textSize":1,"textAlign":"top","captions":[{"inTooltip":true,"isCaption":true,"styles":[],"key":"ASSOCIATED_TO_SSID_SNAPSHOT_FIRST","type":"relationship"}],"captionKeys":[],"styleRules":[]},{"id":"ASSOCIATED_TO_SSID_SNAPSHOT_LAST","name":"ASSOCIATED_TO_SSID_SNAPSHOT_LAST","properties":[],"color":"#848484","size":1,"textSize":1,"textAlign":"top","captions":[{"inTooltip":true,"isCaption":true,"styles":[],"key":"ASSOCIATED_TO_SSID_SNAPSHOT_LAST","type":"relationship"}],"captionKeys":[],"styleRules":[]},{"id":"CONNECTED_TO_AP_SNAPSHOT_CLIENT_SNAPSHOT","name":"CONNECTED_TO_AP_SNAPSHOT_CLIENT_SNAPSHOT","properties":[],"color":"#848484","size":1,"textSize":1,"textAlign":"top","captions":[{"inTooltip":true,"isCaption":true,"styles":[],"key":"CONNECTED_TO_AP_SNAPSHOT_CLIENT_SNAPSHOT","type":"relationship"}],"captionKeys":[],"styleRules":[]},{"id":"CONNECTED_TO_AP_SNAPSHOT_WIFI_DEVICE_SNAPSHOT","name":"CONNECTED_TO_AP_SNAPSHOT_WIFI_DEVICE_SNAPSHOT","properties":[],"color":"#848484","size":1,"textSize":1,"textAlign":"top","captions":[{"inTooltip":true,"isCaption":true,"styles":[],"key":"CONNECTED_TO_AP_SNAPSHOT_WIFI_DEVICE_SNAPSHOT","type":"relationship"}],"captionKeys":[],"styleRules":[]},{"id":"CONNECTED_TO_AP_SNAPSHOT_WIFI_BRIDGE_SNAPSHOT","name":"CONNECTED_TO_AP_SNAPSHOT_WIFI_BRIDGE_SNAPSHOT","properties":[],"color":"#848484","size":1,"textSize":1,"textAlign":"top","captions":[{"inTooltip":true,"isCaption":true,"styles":[],"key":"CONNECTED_TO_AP_SNAPSHOT_WIFI_BRIDGE_SNAPSHOT","type":"relationship"}],"captionKeys":[],"styleRules":[]},{"id":"BEACONED_SSID_AP","name":"BEACONED_SSID_AP","properties":[],"color":"#848484","size":1,"textSize":1,"textAlign":"top","captions":[{"inTooltip":true,"isCaption":true,"styles":[],"key":"BEACONED_SSID_AP","type":"relationship"}],"captionKeys":[],"styleRules":[]},{"id":"RESPONDING_FOR_SSID_AP","name":"RESPONDING_FOR_SSID_AP","properties":[],"color":"#848484","size":1,"textSize":1,"textAlign":"top","captions":[{"inTooltip":true,"isCaption":true,"styles":[],"key":"RESPONDING_FOR_SSID_AP","type":"relationship"}],"captionKeys":[],"styleRules":[]},{"id":"ADVERTISING_FOR_SSID_AP","name":"ADVERTISING_FOR_SSID_AP","properties":[],"color":"#848484","size":1,"textSize":1,"textAlign":"top","captions":[{"inTooltip":true,"isCaption":true,"styles":[],"key":"ADVERTISING_FOR_SSID_AP","type":"relationship"}],"captionKeys":[],"styleRules":[]},{"id":"PROBING_FOR_SSID_CLIENT","name":"PROBING_FOR_SSID_CLIENT","properties":[],"color":"#848484","size":1,"textSize":1,"textAlign":"top","captions":[{"inTooltip":true,"isCaption":true,"styles":[],"key":"PROBING_FOR_SSID_CLIENT","type":"relationship"}],"captionKeys":[],"styleRules":[]},{"id":"NEXT_WIFI_BRIDGE_SNAPSHOT","name":"NEXT_WIFI_BRIDGE_SNAPSHOT","properties":[],"color":"#848484","size":1,"textSize":1,"textAlign":"top","captions":[{"inTooltip":true,"isCaption":true,"styles":[],"key":"NEXT_WIFI_BRIDGE_SNAPSHOT","type":"relationship"}],"captionKeys":[],"styleRules":[]},{"id":"NEXT_ACCESS_POINT_SNAPSHOT","name":"NEXT_ACCESS_POINT_SNAPSHOT","properties":[],"color":"#848484","size":1,"textSize":1,"textAlign":"top","captions":[{"inTooltip":true,"isCaption":true,"styles":[],"key":"NEXT_ACCESS_POINT_SNAPSHOT","type":"relationship"}],"captionKeys":[],"styleRules":[]},{"id":"NEXT_WIFI_DEVICE_SNAPSHOT","name":"NEXT_WIFI_DEVICE_SNAPSHOT","properties":[],"color":"#848484","size":1,"textSize":1,"textAlign":"top","captions":[{"inTooltip":true,"isCaption":true,"styles":[],"key":"NEXT_WIFI_DEVICE_SNAPSHOT","type":"relationship"}],"captionKeys":[],"styleRules":[]},{"id":"NEXT_SSID_SNAPSHOT","name":"NEXT_SSID_SNAPSHOT","properties":[],"color":"#848484","size":1,"textSize":1,"textAlign":"top","captions":[{"inTooltip":true,"isCaption":true,"styles":[],"key":"NEXT_SSID_SNAPSHOT","type":"relationship"}],"captionKeys":[],"styleRules":[]},{"id":"PROBING_FOR_SSID_AP","name":"PROBING_FOR_SSID_AP","properties":[],"color":"#848484","size":1,"textSize":1,"textAlign":"top","captions":[{"inTooltip":true,"isCaption":true,"styles":[],"key":"PROBING_FOR_SSID_AP","type":"relationship"}],"captionKeys":[],"styleRules":[]},{"id":"HAS_SAME_ISOLATED_SUB_NET","name":"HAS_SAME_ISOLATED_SUB_NET","properties":[],"color":"#848484","size":1,"textSize":1,"textAlign":"top","captions":[{"inTooltip":true,"isCaption":true,"styles":[],"key":"HAS_SAME_ISOLATED_SUB_NET","type":"relationship"}],"captionKeys":[],"styleRules":[]}],"palette":{"colors":["#FFE081","#C990C0","#F79767","#57C7E3","#F16667","#D9C8AE","#8DCC93","#ECB5C9","#4C8EDA","#FFC454","#DA7194","#569480","#848484","#D9D9D9"],"currentIndex":27},"createdAt":1733768519510,"lastEditedAt":1733768519510,"templates":[{"name":"Return unsecure networks","id":"tmpl:1734454324161","createdAt":1734454324161,"text":"04 - Show all insecure networks","cypher":"MATCH (ap:`Access Point`)-[:ASSOCIATED_TO_ACCESS_POINT_SNAPSHOT_FIRST|ASSOCIATED_TO_ACCESS_POINT_SNAPSHOT_LAST]->(apsnap:`Access Point Snapshot`)-[:`ASSOCIATED_TO_ACCESS_POINT_SECURITY_POSTURE`]->(aps:`Access Point Security Posture`)\nWHERE aps.apCrypt = 'WEP'\nRETURN ap","isUpdateQuery":null,"isWriteTransactionChecked":null,"params":[],"hasCypherErrors":false},{"name":"Return all relationship until 3 levels from specified client","id":"tmpl:1733945730482","createdAt":1733945730482,"text":"03 - All relationships of client $name until 3 levels","cypher":"MATCH path = (:Client {clientCname:$name})-[*..3]-() return path\n\n//00:D7:6D:11:01:20","isUpdateQuery":null,"isWriteTransactionChecked":null,"params":[{"name":"$name","dataType":"String","collapsed":false,"suggestionLabel":"Client","suggestionProp":"clientCname","suggestionBoolean":false,"cypher":null}],"hasCypherErrors":false},{"name":"Return all wifi devices from the manufacture specified.","id":"tmpl:1733944263364","createdAt":1733944263364,"text":"01 - Find all wifi devices from manufacture $name","cypher":"MATCH (w:`WIFI Device`) WHERE w.deviceManufac =  $name RETURN w","isUpdateQuery":null,"isWriteTransactionChecked":null,"params":[{"name":"$name","dataType":"String","collapsed":false,"suggestionLabel":"WIFI Device","suggestionProp":"deviceManufac","suggestionBoolean":false,"cypher":null}],"hasCypherErrors":false},{"name":"Return all clients from the manufacture specified.","id":"tmpl:1733768519777","createdAt":1733768519777,"text":"02 - Find all clients from manufacture $name","cypher":"MATCH (cli:Client)where cli.clientManufac = $name return cli ","isUpdateQuery":null,"isWriteTransactionChecked":null,"params":[{"name":"$name","dataType":"String","collapsed":false,"suggestionLabel":"Client","suggestionProp":"clientManufac","suggestionBoolean":false,"cypher":null}],"hasCypherErrors":false}],"sceneActions":[],"hiddenRelationshipTypes":[],"hiddenCategories":[],"hideUncategorisedData":false,"type":"STANDARD_PERSPECTIVE","parentPerspectiveId":null,"metadata":{"pathSegments":[{"source":"WIFI Bridge Snapshot","relationshipType":"ASSOCIATED_TO_WIFI_BRIDGE_DEVICE_MOBILITY","target":"WIFI Bridge Device Mobility"},{"source":"SSID Snapshot","relationshipType":"NEXT_SSID_SNAPSHOT","target":"SSID Snapshot"},{"source":"WIFI Device Snapshot","relationshipType":"ASSOCIATED_TO_WIFI_DEVICE_SIGNAL","target":"WIFI Device Signal"},{"source":"Access Point Snapshot","relationshipType":"RESPONDING_FOR_SSID_AP","target":"SSID Snapshot"},{"source":"WIFI Bridge","relationshipType":"ASSOCIATED_TO_WIFI_BRIDGE_SNAPSHOT_LAST","target":"WIFI Bridge Snapshot"},{"source":"SSID","relationshipType":"ASSOCIATED_TO_SSID_SNAPSHOT_LAST","target":"SSID Snapshot"},{"source":"Access Point Snapshot","relationshipType":"ASSOCIATED_TO_ACCESS_POINT_SIGNAL","target":"Access Point Signal"},{"source":"WIFI Device","relationshipType":"ASSOCIATED_TO_WIFI_DEVICE_SNAPSHOT_LAST","target":"WIFI Device Snapshot"},{"source":"WIFI Device Snapshot","relationshipType":"CONNECTED_TO_AP_SNAPSHOT_WIFI_DEVICE_SNAPSHOT","target":"Access Point Snapshot"},{"source":"Access Point","relationshipType":"ASSOCIATED_TO_ACCESS_POINT_SNAPSHOT_LAST","target":"Access Point Snapshot"},{"source":"Client Snapshot","relationshipType":"ASSOCIATED_TO_CLIENT_PERFORMANCE","target":"Client Performance"},{"source":"WIFI Device Snapshot","relationshipType":"ASSOCIATED_TO_WIFI_DEVICE_SECURITY_POSTURE","target":"WIFI Device Security Posture"},{"source":"Access Point","relationshipType":"HAS_SAME_ISOLATED_SUB_NET","target":"Client"},{"source":"SSID","relationshipType":"HAS_SAME_ISOLATED_SUB_NET","target":"WIFI Bridge"},{"source":"Client","relationshipType":"HAS_SAME_ISOLATED_SUB_NET","target":"WIFI Bridge"},{"source":"SSID","relationshipType":"HAS_SAME_ISOLATED_SUB_NET","target":"SSID"},{"source":"SSID","relationshipType":"HAS_SAME_ISOLATED_SUB_NET","target":"Access Point"},{"source":"SSID","relationshipType":"HAS_SAME_ISOLATED_SUB_NET","target":"Client"},{"source":"WIFI Bridge","relationshipType":"HAS_SAME_ISOLATED_SUB_NET","target":"Client"},{"source":"WIFI Device","relationshipType":"HAS_SAME_ISOLATED_SUB_NET","target":"WIFI Bridge"},{"source":"WIFI Bridge","relationshipType":"HAS_SAME_ISOLATED_SUB_NET","target":"WIFI Device"},{"source":"Access Point","relationshipType":"HAS_SAME_ISOLATED_SUB_NET","target":"WIFI Device"},{"source":"WIFI Device","relationshipType":"HAS_SAME_ISOLATED_SUB_NET","target":"SSID"},{"source":"Client","relationshipType":"HAS_SAME_ISOLATED_SUB_NET","target":"SSID"},{"source":"WIFI Bridge","relationshipType":"HAS_SAME_ISOLATED_SUB_NET","target":"SSID"},{"source":"Client","relationshipType":"HAS_SAME_ISOLATED_SUB_NET","target":"Client"},{"source":"Access Point","relationshipType":"HAS_SAME_ISOLATED_SUB_NET","target":"WIFI Bridge"},{"source":"WIFI Device","relationshipType":"HAS_SAME_ISOLATED_SUB_NET","target":"Access Point"},{"source":"Client","relationshipType":"HAS_SAME_ISOLATED_SUB_NET","target":"WIFI Device"},{"source":"Access Point","relationshipType":"HAS_SAME_ISOLATED_SUB_NET","target":"SSID"},{"source":"WIFI Device","relationshipType":"HAS_SAME_ISOLATED_SUB_NET","target":"Client"},{"source":"WIFI Bridge","relationshipType":"HAS_SAME_ISOLATED_SUB_NET","target":"WIFI Bridge"},{"source":"Client","relationshipType":"HAS_SAME_ISOLATED_SUB_NET","target":"Access Point"},{"source":"SSID","relationshipType":"HAS_SAME_ISOLATED_SUB_NET","target":"WIFI Device"},{"source":"WIFI Bridge","relationshipType":"HAS_SAME_ISOLATED_SUB_NET","target":"Access Point"},{"source":"Access Point","relationshipType":"HAS_SAME_ISOLATED_SUB_NET","target":"Access Point"},{"source":"WIFI Device","relationshipType":"HAS_SAME_ISOLATED_SUB_NET","target":"WIFI Device"},{"source":"WIFI Bridge Snapshot","relationshipType":"CONNECTED_TO_AP_SNAPSHOT_WIFI_BRIDGE_SNAPSHOT","target":"Access Point Snapshot"},{"source":"Access Point Snapshot","relationshipType":"BEACONED_SSID_AP","target":"SSID Snapshot"},{"source":"WIFI Bridge Snapshot","relationshipType":"NEXT_WIFI_BRIDGE_SNAPSHOT","target":"WIFI Bridge Snapshot"},{"source":"WIFI Device Snapshot","relationshipType":"ASSOCIATED_TO_WIFI_DEVICE_MOBILITY","target":"WIFI Device Mobility"},{"source":"Client","relationshipType":"ASSOCIATED_TO_CLIENT_SNAPSHOT_FIRST","target":"Client Snapshot"},{"source":"WIFI Bridge Snapshot","relationshipType":"ASSOCIATED_TO_WIFI_BRIDGE_PERFORMANCE","target":"WIFI Bridge Performance"},{"source":"Client Snapshot","relationshipType":"CONNECTED_TO_AP_SNAPSHOT_CLIENT_SNAPSHOT","target":"Access Point Snapshot"},{"source":"WIFI Device","relationshipType":"ASSOCIATED_TO_WIFI_DEVICE_SNAPSHOT_FIRST","target":"WIFI Device Snapshot"},{"source":"Client Snapshot","relationshipType":"ASSOCIATED_TO_CLIENT_SIGNAL","target":"Client Signal"},{"source":"WIFI Device Snapshot","relationshipType":"ASSOCIATED_TO_WIFI_DEVICE_PERFORMANCE","target":"WIFI Device Performance"},{"source":"WIFI Bridge Snapshot","relationshipType":"ASSOCIATED_TO_WIFI_BRIDGE_SIGNAL","target":"WIFI Bridge Signal"},{"source":"SSID","relationshipType":"ASSOCIATED_TO_SSID_SNAPSHOT_FIRST","target":"SSID Snapshot"},{"source":"WIFI Bridge","relationshipType":"ASSOCIATED_TO_WIFI_BRIDGE_SNAPSHOT_FIRST","target":"WIFI Bridge Snapshot"},{"source":"Access Point Snapshot","relationshipType":"NEXT_ACCESS_POINT_SNAPSHOT","target":"Access Point Snapshot"},{"source":"WIFI Device Snapshot","relationshipType":"NEXT_WIFI_DEVICE_SNAPSHOT","target":"WIFI Device Snapshot"},{"source":"Access Point Snapshot","relationshipType":"PROBING_FOR_SSID_AP","target":"SSID Snapshot"},{"source":"WIFI Bridge Snapshot","relationshipType":"ASSOCIATED_TO_WIFI_BRIDGE_SECURITY_POSTURE","target":"WIFI Bridge Security Posture"},{"source":"Access Point Snapshot","relationshipType":"ASSOCIATED_TO_ACCESS_POINT_DEVICE_MOBILITY","target":"Access Point Device Mobility"},{"source":"Client","relationshipType":"ASSOCIATED_TO_CLIENT_SNAPSHOT_LAST","target":"Client Snapshot"},{"source":"Access Point Snapshot","relationshipType":"ASSOCIATED_TO_ACCESS_POINT_PERFORMANCE","target":"Access Point Performance"},{"source":"Access Point Snapshot","relationshipType":"ASSOCIATED_TO_ACCESS_POINT_SECURITY_POSTURE","target":"Access Point Security Posture"},{"source":"Client Snapshot","relationshipType":"ASSOCIATED_TO_CLIENT_DEVICE_MOBILITY","target":"Client Device Mobility"},{"source":"Client Snapshot","relationshipType":"ASSOCIATED_TO_CLIENT_SECURITY_POSTURE","target":"Client Security Posture"},{"source":"Access Point Snapshot","relationshipType":"ADVERTISING_FOR_SSID_AP","target":"SSID Snapshot"},{"source":"Access Point","relationshipType":"ASSOCIATED_TO_ACCESS_POINT_SNAPSHOT_FIRST","target":"Access Point Snapshot"},{"source":"Client Snapshot","relationshipType":"PROBING_FOR_SSID_CLIENT","target":"SSID Snapshot"},{"source":"Client Snapshot","relationshipType":"NEXT_CLIENT_SNAPSHOT","target":"Client Snapshot"}],"indexes":[{"label":"WIFI Device Snapshot","type":"native","propertyKeys":[{"key":"devicesnapId","metadataProp":false},{"key":"devicesnapLastseen","metadataProp":false},{"key":"devicesnapNcaps","metadataProp":false},{"key":"devicesnapNprssid","metadataProp":false},{"key":"devicesnapSignalstr","metadataProp":false},{"key":"devicesnapKey","metadataProp":false},{"key":"devicesnapTimestamp","metadataProp":false},{"key":"devicesnapLbssid","metadataProp":false},{"key":"devicesnapModtime","metadataProp":false},{"key":"devicesnapFirstseen","metadataProp":false},{"key":"wccFullvalue","metadataProp":true}]},{"label":"Access Point Signal","type":"native","propertyKeys":[{"key":"apId","metadataProp":false},{"key":"apChannel","metadataProp":false},{"key":"apLast","metadataProp":false},{"key":"apMax","metadataProp":false},{"key":"apMin","metadataProp":false},{"key":"apFrequency","metadataProp":false},{"key":"wccFullvalue","metadataProp":true}]},{"label":"WIFI Bridge","type":"native","propertyKeys":[{"key":"brdKey","metadataProp":false},{"key":"brdCname","metadataProp":false},{"key":"brdType","metadataProp":false},{"key":"brdName","metadataProp":false},{"key":"brdPhy","metadataProp":false},{"key":"brdMac","metadataProp":false},{"key":"brdManufac","metadataProp":false},{"key":"wccFullvalue","metadataProp":true}]},{"label":"SSID Snapshot","type":"native","propertyKeys":[{"key":"ssidsnapId","metadataProp":false},{"key":"ssidsnapHash","metadataProp":false},{"key":"ssidsnapRespondingdevices","metadataProp":false},{"key":"ssidsnapTimestamp","metadataProp":false},{"key":"ssidsnapName","metadataProp":false},{"key":"ssidsnapProbingdevices","metadataProp":false},{"key":"ssidsnapAdvertisingdevices","metadataProp":false},{"key":"wccFullvalue","metadataProp":true},{"key":"ssidsnapProbingDevices","metadataProp":true}]},{"label":"WIFI Device Performance","type":"native","propertyKeys":[{"key":"deviceperfId","metadataProp":false},{"key":"deviceperfMaxtxpw","metadataProp":false},{"key":"deviceperfDatasize","metadataProp":false},{"key":"deviceperfDatasizeretry","metadataProp":false},{"key":"deviceperfMintxpw","metadataProp":false},{"key":"deviceperfLinkmeasure","metadataProp":false},{"key":"wccFullvalue","metadataProp":true}]},{"label":"Client","type":"native","propertyKeys":[{"key":"clientKey","metadataProp":false},{"key":"clientType","metadataProp":false},{"key":"clientName","metadataProp":false},{"key":"clientPhy","metadataProp":false},{"key":"clientCname","metadataProp":false},{"key":"clientManufac","metadataProp":false},{"key":"clientMac","metadataProp":false},{"key":"wccFullvalue","metadataProp":true}]},{"label":"Access Point Security Posture","type":"native","propertyKeys":[{"key":"apId","metadataProp":false},{"key":"apWpscount","metadataProp":false},{"key":"apNfrag","metadataProp":false},{"key":"apLastbssid","metadataProp":false},{"key":"apProbedSSIDs","metadataProp":false},{"key":"apKey","metadataProp":false},{"key":"apWpslast","metadataProp":false},{"key":"apNretries","metadataProp":false},{"key":"apCrypt","metadataProp":false},{"key":"wccFullvalue","metadataProp":true}]},{"label":"Access Point","type":"native","propertyKeys":[{"key":"apKey","metadataProp":false},{"key":"apCname","metadataProp":false},{"key":"apName","metadataProp":false},{"key":"apType","metadataProp":false},{"key":"apPhy","metadataProp":false},{"key":"apMac","metadataProp":false},{"key":"apManufac","metadataProp":false},{"key":"wccFullvalue","metadataProp":true}]},{"label":"WIFI Bridge Device Mobility","type":"native","propertyKeys":[{"key":"brdId","metadataProp":false},{"key":"brdKey","metadataProp":false},{"key":"brdSeenbycount","metadataProp":false},{"key":"brdLastbssid","metadataProp":false},{"key":"brdSignalchange","metadataProp":false},{"key":"brdLastseen","metadataProp":false},{"key":"brdFirstseen","metadataProp":false},{"key":"wccFullvalue","metadataProp":true}]},{"label":"WIFI Bridge Performance","type":"native","propertyKeys":[{"key":"brdId","metadataProp":false},{"key":"brdMintxpw","metadataProp":false},{"key":"brdDatasize","metadataProp":false},{"key":"brdLinkmeasure","metadataProp":false},{"key":"brdDatasizeretry","metadataProp":false},{"key":"brdMaxtxpw","metadataProp":false},{"key":"wccFullvalue","metadataProp":true}]},{"label":"Client Snapshot","type":"native","propertyKeys":[{"key":"csnapId","metadataProp":false},{"key":"csnapSignalstr","metadataProp":false},{"key":"csnapModtime","metadataProp":false},{"key":"csnapLbssid","metadataProp":false},{"key":"csnapTimestamp","metadataProp":false},{"key":"csnapNcaps","metadataProp":false},{"key":"csnapFirstseen","metadataProp":false},{"key":"csnapNprssid","metadataProp":false},{"key":"csnapKey","metadataProp":false},{"key":"csnapLastseen","metadataProp":false},{"key":"wccFullvalue","metadataProp":true}]},{"label":"WIFI Device Security Posture","type":"native","propertyKeys":[{"key":"devicespId","metadataProp":false},{"key":"devicespKey","metadataProp":false},{"key":"devicespNfrag","metadataProp":false},{"key":"devicespCrypt","metadataProp":false},{"key":"devicespWpscount","metadataProp":false},{"key":"devicespLastbssid","metadataProp":false},{"key":"devicespProbedSSIDs","metadataProp":false},{"key":"devicespWpslast","metadataProp":false},{"key":"devicespNretries","metadataProp":false},{"key":"wccFullvalue","metadataProp":true}]},{"label":"SSID","type":"native","propertyKeys":[{"key":"ssidHash","metadataProp":false},{"key":"ssidProbingdvlen","metadataProp":false},{"key":"ssidFirstseen","metadataProp":false},{"key":"ssidAdvdvlen","metadataProp":false},{"key":"ssidEncryptionitem","metadataProp":false},{"key":"ssidName","metadataProp":false},{"key":"ssideRespdvlen","metadataProp":false},{"key":"ssidEncryption","metadataProp":false},{"key":"ssidLastseen","metadataProp":false},{"key":"wccFullvalue","metadataProp":true}]},{"label":"Client Security Posture","type":"native","propertyKeys":[{"key":"cspId","metadataProp":false},{"key":"cspLastbssid","metadataProp":false},{"key":"cspNretries","metadataProp":false},{"key":"cspCrypt","metadataProp":false},{"key":"cspWpslast","metadataProp":false},{"key":"cspKey","metadataProp":false},{"key":"cspWpscount","metadataProp":false},{"key":"cspNfrag","metadataProp":false},{"key":"cspProbedSSIDs","metadataProp":false},{"key":"wccFullvalue","metadataProp":true}]},{"label":"Client Performance","type":"native","propertyKeys":[{"key":"cperfId","metadataProp":false},{"key":"cperfDatasizeretry","metadataProp":false},{"key":"cperfDatasize","metadataProp":false},{"key":"cperfLinkmeasure","metadataProp":false},{"key":"cperfMintxpw","metadataProp":false},{"key":"cperfMaxtxpw","metadataProp":false},{"key":"wccFullvalue","metadataProp":true}]},{"label":"WIFI Device Mobility","type":"native","propertyKeys":[{"key":"devicemobId","metadataProp":false},{"key":"devicemobLastbssid","metadataProp":false},{"key":"devicemobFirstseen","metadataProp":false},{"key":"devicemobSignalchange","metadataProp":false},{"key":"devicemobLastseen","metadataProp":false},{"key":"devicemobKey","metadataProp":false},{"key":"devicemobSeenbycount","metadataProp":false},{"key":"wccFullvalue","metadataProp":true}]},{"label":"WIFI Device","type":"native","propertyKeys":[{"key":"deviceKey","metadataProp":false},{"key":"deviceName","metadataProp":false},{"key":"deviceManufac","metadataProp":false},{"key":"deviceCname","metadataProp":false},{"key":"devicePhy","metadataProp":false},{"key":"deviceMac","metadataProp":false},{"key":"deviceType","metadataProp":false},{"key":"wccFullvalue","metadataProp":true}]},{"label":"Client Device Mobility","type":"native","propertyKeys":[{"key":"cdmobId","metadataProp":false},{"key":"cdmobFirstseen","metadataProp":false},{"key":"cdmobSeenbycount","metadataProp":false},{"key":"cdmobLastbssid","metadataProp":false},{"key":"cdmobKey","metadataProp":false},{"key":"cdmobSignalchange","metadataProp":false},{"key":"cdmobLastseen","metadataProp":false},{"key":"wccFullvalue","metadataProp":true}]},{"label":"WIFI Bridge Signal","type":"native","propertyKeys":[{"key":"brdId","metadataProp":false},{"key":"brdFrequency","metadataProp":false},{"key":"brdLast","metadataProp":false},{"key":"brdChannelx","metadataProp":false},{"key":"brdMax","metadataProp":false},{"key":"brdMin","metadataProp":false},{"key":"wccFullvalue","metadataProp":true},{"key":"brdChannel","metadataProp":true}]},{"label":"WIFI Bridge Snapshot","type":"native","propertyKeys":[{"key":"brdsnapId","metadataProp":false},{"key":"brdsnapNprssid","metadataProp":false},{"key":"brdsnapModtime","metadataProp":false},{"key":"brdsnapLastseen","metadataProp":false},{"key":"brdsnapLbssid","metadataProp":false},{"key":"brdsnapNcaps","metadataProp":false},{"key":"brdsnapTimestamp","metadataProp":false},{"key":"brdsnapFirstseen","metadataProp":false},{"key":"brdsnapKey","metadataProp":false},{"key":"brdsnapSignalstr","metadataProp":false},{"key":"wccFullvalue","metadataProp":true}]},{"label":"Access Point Device Mobility","type":"native","propertyKeys":[{"key":"apId","metadataProp":false},{"key":"apKey","metadataProp":false},{"key":"apSignalchange","metadataProp":false},{"key":"apFirstseen","metadataProp":false},{"key":"apLastbssid","metadataProp":false},{"key":"apSeenbycount","metadataProp":false},{"key":"apLastseen","metadataProp":false},{"key":"wccFullvalue","metadataProp":true}]},{"label":"Access Point Performance","type":"native","propertyKeys":[{"key":"apId","metadataProp":false},{"key":"apDatasizeretry","metadataProp":false},{"key":"apMaxtxpw","metadataProp":false},{"key":"apDatasize","metadataProp":false},{"key":"apMintxpw","metadataProp":false},{"key":"apLinkmeasure","metadataProp":false},{"key":"wccFullvalue","metadataProp":true}]},{"label":"WIFI Bridge Security Posture","type":"native","propertyKeys":[{"key":"brdId","metadataProp":false},{"key":"brdKey","metadataProp":false},{"key":"brdProbedSSIDs","metadataProp":false},{"key":"brdNfrag","metadataProp":false},{"key":"brdLastbssid","metadataProp":false},{"key":"brdNretries","metadataProp":false},{"key":"brdCrypt","metadataProp":false},{"key":"brdWpscount","metadataProp":false},{"key":"brdWpslast","metadataProp":false},{"key":"wccFullvalue","metadataProp":true}]},{"label":"Client Signal","type":"native","propertyKeys":[{"key":"csId","metadataProp":false},{"key":"csLast","metadataProp":false},{"key":"csMin","metadataProp":false},{"key":"csMax","metadataProp":false},{"key":"csFrequency","metadataProp":false},{"key":"csChannel","metadataProp":false},{"key":"wccFullvalue","metadataProp":true}]},{"label":"WIFI Device Signal","type":"native","propertyKeys":[{"key":"devicesignalId","metadataProp":false},{"key":"devicesignalLast","metadataProp":false},{"key":"devicesignalMin","metadataProp":false},{"key":"devicesignalMax","metadataProp":false},{"key":"devicesignalChannel","metadataProp":false},{"key":"devicesignalFrequency","metadataProp":false},{"key":"wccFullvalue","metadataProp":true}]},{"label":"Access Point Snapshot","type":"native","propertyKeys":[{"key":"apsnapId","metadataProp":false},{"key":"apsnapTimestamp","metadataProp":false},{"key":"apsnapNcaps","metadataProp":false},{"key":"apsnapSignalstr","metadataProp":false},{"key":"apsnapNprssid","metadataProp":false},{"key":"apsnapLbssid","metadataProp":false},{"key":"apsnapFirstseen","metadataProp":false},{"key":"apsnapKey","metadataProp":false},{"key":"apsnapLastseen","metadataProp":false},{"key":"apsnapModtime","metadataProp":false},{"key":"wccFullvalue","metadataProp":true}]},{"label":null,"type":"native","propertyKeys":[]},{"label":"_Neodash_Dashboard","type":"native","isMetadataPropIndex":true,"propertyKeys":[{"key":"uuid","metadataProp":true},{"key":"user","metadataProp":true},{"key":"content","metadataProp":true},{"key":"title","metadataProp":true},{"key":"date","metadataProp":true},{"key":"version","metadataProp":true}]}]},"version":"2.19.0"}